package com.umeng.analytics.pro;

import android.content.Context;
import android.content.SharedPreferences;
import android.content.SharedPreferences.Editor;
import android.text.TextUtils;
import android.util.Base64;
import java.util.ArrayList;
import java.util.List;
import org.json.JSONObject;

public class w
{
  public static final int a = 2049;
  public static final int b = 2050;
  private static Context c = null;
  private static String d = null;
  private static final String e = "umeng+";
  private static final String f = "ek__id";
  private static final String g = "ek_key";
  private List<String> h = new ArrayList();
  
  private w()
  {
    if (c != null)
    {
      b();
      this.h.clear();
    }
  }
  
  public static final w a(Context paramContext)
  {
    c = paramContext;
    return b.a();
  }
  
  /* Error */
  private void a(String paramString1, JSONObject paramJSONObject, android.database.sqlite.SQLiteDatabase paramSQLiteDatabase, String paramString2)
    throws org.json.JSONException
  {
    // Byte code:
    //   0: aconst_null
    //   1: astore 5
    //   3: aconst_null
    //   4: astore 6
    //   6: aload_3
    //   7: new 66	java/lang/StringBuilder
    //   10: dup
    //   11: invokespecial 67	java/lang/StringBuilder:<init>	()V
    //   14: ldc 69
    //   16: invokevirtual 73	java/lang/StringBuilder:append	(Ljava/lang/String;)Ljava/lang/StringBuilder;
    //   19: aload 4
    //   21: invokevirtual 73	java/lang/StringBuilder:append	(Ljava/lang/String;)Ljava/lang/StringBuilder;
    //   24: ldc 75
    //   26: invokevirtual 73	java/lang/StringBuilder:append	(Ljava/lang/String;)Ljava/lang/StringBuilder;
    //   29: ldc 77
    //   31: invokevirtual 73	java/lang/StringBuilder:append	(Ljava/lang/String;)Ljava/lang/StringBuilder;
    //   34: ldc 79
    //   36: invokevirtual 73	java/lang/StringBuilder:append	(Ljava/lang/String;)Ljava/lang/StringBuilder;
    //   39: ldc 81
    //   41: invokevirtual 73	java/lang/StringBuilder:append	(Ljava/lang/String;)Ljava/lang/StringBuilder;
    //   44: ldc 83
    //   46: invokevirtual 73	java/lang/StringBuilder:append	(Ljava/lang/String;)Ljava/lang/StringBuilder;
    //   49: aload_1
    //   50: invokevirtual 73	java/lang/StringBuilder:append	(Ljava/lang/String;)Ljava/lang/StringBuilder;
    //   53: ldc 85
    //   55: invokevirtual 73	java/lang/StringBuilder:append	(Ljava/lang/String;)Ljava/lang/StringBuilder;
    //   58: invokevirtual 89	java/lang/StringBuilder:toString	()Ljava/lang/String;
    //   61: aconst_null
    //   62: invokevirtual 95	android/database/sqlite/SQLiteDatabase:rawQuery	(Ljava/lang/String;[Ljava/lang/String;)Landroid/database/Cursor;
    //   65: astore 7
    //   67: aload 7
    //   69: astore 5
    //   71: aload 5
    //   73: ifnull +200 -> 273
    //   76: aload 5
    //   78: invokeinterface 101 1 0
    //   83: ifeq +196 -> 279
    //   86: aload_0
    //   87: aload 5
    //   89: aload 5
    //   91: aload 4
    //   93: invokeinterface 105 2 0
    //   98: invokeinterface 109 2 0
    //   103: invokevirtual 112	com/umeng/analytics/pro/w:b	(Ljava/lang/String;)Ljava/lang/String;
    //   106: astore 6
    //   108: goto -32 -> 76
    //   111: new 114	org/json/JSONArray
    //   114: dup
    //   115: invokespecial 115	org/json/JSONArray:<init>	()V
    //   118: astore 7
    //   120: aload 6
    //   122: invokestatic 121	android/text/TextUtils:isEmpty	(Ljava/lang/CharSequence;)Z
    //   125: ifne +14 -> 139
    //   128: new 114	org/json/JSONArray
    //   131: dup
    //   132: aload 6
    //   134: invokespecial 124	org/json/JSONArray:<init>	(Ljava/lang/String;)V
    //   137: astore 7
    //   139: aload 7
    //   141: aload_2
    //   142: invokevirtual 128	org/json/JSONArray:put	(Ljava/lang/Object;)Lorg/json/JSONArray;
    //   145: pop
    //   146: aload_0
    //   147: aload 7
    //   149: invokevirtual 129	org/json/JSONArray:toString	()Ljava/lang/String;
    //   152: invokevirtual 131	com/umeng/analytics/pro/w:a	(Ljava/lang/String;)Ljava/lang/String;
    //   155: astore_2
    //   156: aload_2
    //   157: invokestatic 121	android/text/TextUtils:isEmpty	(Ljava/lang/CharSequence;)Z
    //   160: ifne +60 -> 220
    //   163: aload_3
    //   164: new 66	java/lang/StringBuilder
    //   167: dup
    //   168: invokespecial 67	java/lang/StringBuilder:<init>	()V
    //   171: ldc -123
    //   173: invokevirtual 73	java/lang/StringBuilder:append	(Ljava/lang/String;)Ljava/lang/StringBuilder;
    //   176: aload 4
    //   178: invokevirtual 73	java/lang/StringBuilder:append	(Ljava/lang/String;)Ljava/lang/StringBuilder;
    //   181: ldc 83
    //   183: invokevirtual 73	java/lang/StringBuilder:append	(Ljava/lang/String;)Ljava/lang/StringBuilder;
    //   186: aload_2
    //   187: invokevirtual 73	java/lang/StringBuilder:append	(Ljava/lang/String;)Ljava/lang/StringBuilder;
    //   190: ldc -121
    //   192: invokevirtual 73	java/lang/StringBuilder:append	(Ljava/lang/String;)Ljava/lang/StringBuilder;
    //   195: ldc 81
    //   197: invokevirtual 73	java/lang/StringBuilder:append	(Ljava/lang/String;)Ljava/lang/StringBuilder;
    //   200: ldc 83
    //   202: invokevirtual 73	java/lang/StringBuilder:append	(Ljava/lang/String;)Ljava/lang/StringBuilder;
    //   205: aload_1
    //   206: invokevirtual 73	java/lang/StringBuilder:append	(Ljava/lang/String;)Ljava/lang/StringBuilder;
    //   209: ldc 85
    //   211: invokevirtual 73	java/lang/StringBuilder:append	(Ljava/lang/String;)Ljava/lang/StringBuilder;
    //   214: invokevirtual 89	java/lang/StringBuilder:toString	()Ljava/lang/String;
    //   217: invokevirtual 138	android/database/sqlite/SQLiteDatabase:execSQL	(Ljava/lang/String;)V
    //   220: aload 5
    //   222: ifnull +10 -> 232
    //   225: aload 5
    //   227: invokeinterface 141 1 0
    //   232: return
    //   233: astore_1
    //   234: aconst_null
    //   235: astore 5
    //   237: aload 5
    //   239: ifnull -7 -> 232
    //   242: aload 5
    //   244: invokeinterface 141 1 0
    //   249: return
    //   250: astore_1
    //   251: aload 5
    //   253: ifnull +10 -> 263
    //   256: aload 5
    //   258: invokeinterface 141 1 0
    //   263: aload_1
    //   264: athrow
    //   265: astore_1
    //   266: goto -15 -> 251
    //   269: astore_1
    //   270: goto -33 -> 237
    //   273: aconst_null
    //   274: astore 6
    //   276: goto -165 -> 111
    //   279: goto -168 -> 111
    // Local variable table:
    //   start	length	slot	name	signature
    //   0	282	0	this	w
    //   0	282	1	paramString1	String
    //   0	282	2	paramJSONObject	JSONObject
    //   0	282	3	paramSQLiteDatabase	android.database.sqlite.SQLiteDatabase
    //   0	282	4	paramString2	String
    //   1	256	5	localObject1	Object
    //   4	271	6	str	String
    //   65	83	7	localObject2	Object
    // Exception table:
    //   from	to	target	type
    //   6	67	233	java/lang/Throwable
    //   6	67	250	finally
    //   76	108	265	finally
    //   111	120	265	finally
    //   120	139	265	finally
    //   139	220	265	finally
    //   76	108	269	java/lang/Throwable
    //   111	120	269	java/lang/Throwable
    //   120	139	269	java/lang/Throwable
    //   139	220	269	java/lang/Throwable
  }
  
  /* Error */
  private void a(JSONObject paramJSONObject)
  {
    // Byte code:
    //   0: aconst_null
    //   1: astore 4
    //   3: getstatic 35	com/umeng/analytics/pro/w:c	Landroid/content/Context;
    //   6: invokestatic 150	com/umeng/analytics/pro/u:a	(Landroid/content/Context;)Lcom/umeng/analytics/pro/u;
    //   9: invokevirtual 153	com/umeng/analytics/pro/u:a	()Landroid/database/sqlite/SQLiteDatabase;
    //   12: astore_3
    //   13: aload_3
    //   14: invokevirtual 156	android/database/sqlite/SQLiteDatabase:beginTransaction	()V
    //   17: goto +720 -> 737
    //   20: aload_3
    //   21: ldc -98
    //   23: aconst_null
    //   24: invokevirtual 95	android/database/sqlite/SQLiteDatabase:rawQuery	(Ljava/lang/String;[Ljava/lang/String;)Landroid/database/Cursor;
    //   27: astore 5
    //   29: aload 5
    //   31: astore 4
    //   33: aload 4
    //   35: ifnull +585 -> 620
    //   38: new 160	org/json/JSONObject
    //   41: dup
    //   42: invokespecial 161	org/json/JSONObject:<init>	()V
    //   45: astore 8
    //   47: new 160	org/json/JSONObject
    //   50: dup
    //   51: invokespecial 161	org/json/JSONObject:<init>	()V
    //   54: astore 7
    //   56: aload 4
    //   58: invokeinterface 101 1 0
    //   63: ifeq +331 -> 394
    //   66: aload 4
    //   68: aload 4
    //   70: ldc -93
    //   72: invokeinterface 105 2 0
    //   77: invokeinterface 167 2 0
    //   82: istore_2
    //   83: aload 4
    //   85: aload 4
    //   87: ldc -87
    //   89: invokeinterface 105 2 0
    //   94: invokeinterface 109 2 0
    //   99: astore 6
    //   101: aload 4
    //   103: aload 4
    //   105: ldc -85
    //   107: invokeinterface 105 2 0
    //   112: invokeinterface 109 2 0
    //   117: astore 9
    //   119: aload 6
    //   121: astore 5
    //   123: ldc -83
    //   125: aload 6
    //   127: invokevirtual 179	java/lang/String:equals	(Ljava/lang/Object;)Z
    //   130: ifeq +610 -> 740
    //   133: invokestatic 183	com/umeng/analytics/pro/bd:a	()Ljava/lang/String;
    //   136: astore 5
    //   138: goto +602 -> 740
    //   141: aload 9
    //   143: invokestatic 121	android/text/TextUtils:isEmpty	(Ljava/lang/CharSequence;)Z
    //   146: ifne -90 -> 56
    //   149: new 160	org/json/JSONObject
    //   152: dup
    //   153: aload_0
    //   154: aload 9
    //   156: invokevirtual 112	com/umeng/analytics/pro/w:b	(Ljava/lang/String;)Ljava/lang/String;
    //   159: invokespecial 184	org/json/JSONObject:<init>	(Ljava/lang/String;)V
    //   162: astore 9
    //   164: aload 8
    //   166: aload 5
    //   168: invokevirtual 188	org/json/JSONObject:has	(Ljava/lang/String;)Z
    //   171: ifeq +73 -> 244
    //   174: aload 8
    //   176: aload 5
    //   178: invokevirtual 192	org/json/JSONObject:optJSONArray	(Ljava/lang/String;)Lorg/json/JSONArray;
    //   181: astore 6
    //   183: aload 6
    //   185: aload 9
    //   187: invokevirtual 128	org/json/JSONArray:put	(Ljava/lang/Object;)Lorg/json/JSONArray;
    //   190: pop
    //   191: aload 8
    //   193: aload 5
    //   195: aload 6
    //   197: invokevirtual 195	org/json/JSONObject:put	(Ljava/lang/String;Ljava/lang/Object;)Lorg/json/JSONObject;
    //   200: pop
    //   201: goto -145 -> 56
    //   204: astore_1
    //   205: aload_3
    //   206: astore_1
    //   207: aload 4
    //   209: astore_3
    //   210: getstatic 35	com/umeng/analytics/pro/w:c	Landroid/content/Context;
    //   213: invokestatic 200	com/umeng/analytics/pro/v:b	(Landroid/content/Context;)V
    //   216: aload_3
    //   217: ifnull +9 -> 226
    //   220: aload_3
    //   221: invokeinterface 141 1 0
    //   226: aload_1
    //   227: ifnull +7 -> 234
    //   230: aload_1
    //   231: invokevirtual 203	android/database/sqlite/SQLiteDatabase:endTransaction	()V
    //   234: getstatic 35	com/umeng/analytics/pro/w:c	Landroid/content/Context;
    //   237: invokestatic 150	com/umeng/analytics/pro/u:a	(Landroid/content/Context;)Lcom/umeng/analytics/pro/u;
    //   240: invokevirtual 204	com/umeng/analytics/pro/u:b	()V
    //   243: return
    //   244: new 114	org/json/JSONArray
    //   247: dup
    //   248: invokespecial 115	org/json/JSONArray:<init>	()V
    //   251: astore 6
    //   253: goto -70 -> 183
    //   256: astore_1
    //   257: aload 4
    //   259: ifnull +10 -> 269
    //   262: aload 4
    //   264: invokeinterface 141 1 0
    //   269: aload_3
    //   270: ifnull +7 -> 277
    //   273: aload_3
    //   274: invokevirtual 203	android/database/sqlite/SQLiteDatabase:endTransaction	()V
    //   277: getstatic 35	com/umeng/analytics/pro/w:c	Landroid/content/Context;
    //   280: invokestatic 150	com/umeng/analytics/pro/u:a	(Landroid/content/Context;)Lcom/umeng/analytics/pro/u;
    //   283: invokevirtual 204	com/umeng/analytics/pro/u:b	()V
    //   286: return
    //   287: aload 9
    //   289: invokestatic 121	android/text/TextUtils:isEmpty	(Ljava/lang/CharSequence;)Z
    //   292: ifne -236 -> 56
    //   295: new 160	org/json/JSONObject
    //   298: dup
    //   299: aload_0
    //   300: aload 9
    //   302: invokevirtual 112	com/umeng/analytics/pro/w:b	(Ljava/lang/String;)Ljava/lang/String;
    //   305: invokespecial 184	org/json/JSONObject:<init>	(Ljava/lang/String;)V
    //   308: astore 9
    //   310: aload 7
    //   312: aload 5
    //   314: invokevirtual 188	org/json/JSONObject:has	(Ljava/lang/String;)Z
    //   317: ifeq +65 -> 382
    //   320: aload 7
    //   322: aload 5
    //   324: invokevirtual 192	org/json/JSONObject:optJSONArray	(Ljava/lang/String;)Lorg/json/JSONArray;
    //   327: astore 6
    //   329: aload 6
    //   331: aload 9
    //   333: invokevirtual 128	org/json/JSONArray:put	(Ljava/lang/Object;)Lorg/json/JSONArray;
    //   336: pop
    //   337: aload 7
    //   339: aload 5
    //   341: aload 6
    //   343: invokevirtual 195	org/json/JSONObject:put	(Ljava/lang/String;Ljava/lang/Object;)Lorg/json/JSONObject;
    //   346: pop
    //   347: goto -291 -> 56
    //   350: astore_1
    //   351: aload 4
    //   353: ifnull +10 -> 363
    //   356: aload 4
    //   358: invokeinterface 141 1 0
    //   363: aload_3
    //   364: ifnull +7 -> 371
    //   367: aload_3
    //   368: invokevirtual 203	android/database/sqlite/SQLiteDatabase:endTransaction	()V
    //   371: getstatic 35	com/umeng/analytics/pro/w:c	Landroid/content/Context;
    //   374: invokestatic 150	com/umeng/analytics/pro/u:a	(Landroid/content/Context;)Lcom/umeng/analytics/pro/u;
    //   377: invokevirtual 204	com/umeng/analytics/pro/u:b	()V
    //   380: aload_1
    //   381: athrow
    //   382: new 114	org/json/JSONArray
    //   385: dup
    //   386: invokespecial 115	org/json/JSONArray:<init>	()V
    //   389: astore 6
    //   391: goto -62 -> 329
    //   394: aload 8
    //   396: invokevirtual 208	org/json/JSONObject:length	()I
    //   399: ifle +108 -> 507
    //   402: new 114	org/json/JSONArray
    //   405: dup
    //   406: invokespecial 115	org/json/JSONArray:<init>	()V
    //   409: astore 5
    //   411: aload 8
    //   413: invokevirtual 212	org/json/JSONObject:keys	()Ljava/util/Iterator;
    //   416: astore 6
    //   418: aload 6
    //   420: invokeinterface 217 1 0
    //   425: ifeq +65 -> 490
    //   428: new 160	org/json/JSONObject
    //   431: dup
    //   432: invokespecial 161	org/json/JSONObject:<init>	()V
    //   435: astore 9
    //   437: aload 6
    //   439: invokeinterface 221 1 0
    //   444: checkcast 175	java/lang/String
    //   447: astore 10
    //   449: aload 9
    //   451: aload 10
    //   453: new 114	org/json/JSONArray
    //   456: dup
    //   457: aload 8
    //   459: aload 10
    //   461: invokevirtual 224	org/json/JSONObject:optString	(Ljava/lang/String;)Ljava/lang/String;
    //   464: invokespecial 124	org/json/JSONArray:<init>	(Ljava/lang/String;)V
    //   467: invokevirtual 195	org/json/JSONObject:put	(Ljava/lang/String;Ljava/lang/Object;)Lorg/json/JSONObject;
    //   470: pop
    //   471: aload 9
    //   473: invokevirtual 208	org/json/JSONObject:length	()I
    //   476: ifle -58 -> 418
    //   479: aload 5
    //   481: aload 9
    //   483: invokevirtual 128	org/json/JSONArray:put	(Ljava/lang/Object;)Lorg/json/JSONArray;
    //   486: pop
    //   487: goto -69 -> 418
    //   490: aload 5
    //   492: invokevirtual 225	org/json/JSONArray:length	()I
    //   495: ifle +12 -> 507
    //   498: aload_1
    //   499: ldc -29
    //   501: aload 5
    //   503: invokevirtual 195	org/json/JSONObject:put	(Ljava/lang/String;Ljava/lang/Object;)Lorg/json/JSONObject;
    //   506: pop
    //   507: aload 7
    //   509: invokevirtual 208	org/json/JSONObject:length	()I
    //   512: ifle +108 -> 620
    //   515: new 114	org/json/JSONArray
    //   518: dup
    //   519: invokespecial 115	org/json/JSONArray:<init>	()V
    //   522: astore 5
    //   524: aload 7
    //   526: invokevirtual 212	org/json/JSONObject:keys	()Ljava/util/Iterator;
    //   529: astore 6
    //   531: aload 6
    //   533: invokeinterface 217 1 0
    //   538: ifeq +65 -> 603
    //   541: new 160	org/json/JSONObject
    //   544: dup
    //   545: invokespecial 161	org/json/JSONObject:<init>	()V
    //   548: astore 8
    //   550: aload 6
    //   552: invokeinterface 221 1 0
    //   557: checkcast 175	java/lang/String
    //   560: astore 9
    //   562: aload 8
    //   564: aload 9
    //   566: new 114	org/json/JSONArray
    //   569: dup
    //   570: aload 7
    //   572: aload 9
    //   574: invokevirtual 224	org/json/JSONObject:optString	(Ljava/lang/String;)Ljava/lang/String;
    //   577: invokespecial 124	org/json/JSONArray:<init>	(Ljava/lang/String;)V
    //   580: invokevirtual 195	org/json/JSONObject:put	(Ljava/lang/String;Ljava/lang/Object;)Lorg/json/JSONObject;
    //   583: pop
    //   584: aload 8
    //   586: invokevirtual 208	org/json/JSONObject:length	()I
    //   589: ifle -58 -> 531
    //   592: aload 5
    //   594: aload 8
    //   596: invokevirtual 128	org/json/JSONArray:put	(Ljava/lang/Object;)Lorg/json/JSONArray;
    //   599: pop
    //   600: goto -69 -> 531
    //   603: aload 5
    //   605: invokevirtual 225	org/json/JSONArray:length	()I
    //   608: ifle +12 -> 620
    //   611: aload_1
    //   612: ldc -27
    //   614: aload 5
    //   616: invokevirtual 195	org/json/JSONObject:put	(Ljava/lang/String;Ljava/lang/Object;)Lorg/json/JSONObject;
    //   619: pop
    //   620: aload_3
    //   621: invokevirtual 232	android/database/sqlite/SQLiteDatabase:setTransactionSuccessful	()V
    //   624: aload 4
    //   626: ifnull +10 -> 636
    //   629: aload 4
    //   631: invokeinterface 141 1 0
    //   636: aload_3
    //   637: ifnull +7 -> 644
    //   640: aload_3
    //   641: invokevirtual 203	android/database/sqlite/SQLiteDatabase:endTransaction	()V
    //   644: getstatic 35	com/umeng/analytics/pro/w:c	Landroid/content/Context;
    //   647: invokestatic 150	com/umeng/analytics/pro/u:a	(Landroid/content/Context;)Lcom/umeng/analytics/pro/u;
    //   650: invokevirtual 204	com/umeng/analytics/pro/u:b	()V
    //   653: return
    //   654: astore_1
    //   655: goto -11 -> 644
    //   658: astore_1
    //   659: goto -425 -> 234
    //   662: astore_1
    //   663: goto -386 -> 277
    //   666: astore_3
    //   667: goto -296 -> 371
    //   670: astore_1
    //   671: aconst_null
    //   672: astore_3
    //   673: aconst_null
    //   674: astore 4
    //   676: goto -325 -> 351
    //   679: astore_1
    //   680: aconst_null
    //   681: astore 4
    //   683: goto -332 -> 351
    //   686: astore 4
    //   688: aload_1
    //   689: astore 5
    //   691: aload 4
    //   693: astore_1
    //   694: aload_3
    //   695: astore 4
    //   697: aload 5
    //   699: astore_3
    //   700: goto -349 -> 351
    //   703: astore_1
    //   704: aconst_null
    //   705: astore 4
    //   707: aconst_null
    //   708: astore_3
    //   709: goto -452 -> 257
    //   712: astore_1
    //   713: aconst_null
    //   714: astore 4
    //   716: goto -459 -> 257
    //   719: astore_1
    //   720: aconst_null
    //   721: astore_1
    //   722: aload 4
    //   724: astore_3
    //   725: goto -515 -> 210
    //   728: astore_1
    //   729: aload_3
    //   730: astore_1
    //   731: aload 4
    //   733: astore_3
    //   734: goto -524 -> 210
    //   737: goto -717 -> 20
    //   740: iload_2
    //   741: tableswitch	default:+23->764, 2049:+-600->141, 2050:+-454->287
    //   764: goto -708 -> 56
    // Local variable table:
    //   start	length	slot	name	signature
    //   0	767	0	this	w
    //   0	767	1	paramJSONObject	JSONObject
    //   82	659	2	i	int
    //   12	629	3	localObject1	Object
    //   666	1	3	localThrowable	Throwable
    //   672	62	3	localObject2	Object
    //   1	681	4	localObject3	Object
    //   686	6	4	localObject4	Object
    //   695	37	4	localObject5	Object
    //   27	671	5	localObject6	Object
    //   99	452	6	localObject7	Object
    //   54	517	7	localJSONObject1	JSONObject
    //   45	550	8	localJSONObject2	JSONObject
    //   117	456	9	localObject8	Object
    //   447	13	10	str	String
    // Exception table:
    //   from	to	target	type
    //   38	56	204	android/database/sqlite/SQLiteDatabaseCorruptException
    //   56	119	204	android/database/sqlite/SQLiteDatabaseCorruptException
    //   123	138	204	android/database/sqlite/SQLiteDatabaseCorruptException
    //   141	183	204	android/database/sqlite/SQLiteDatabaseCorruptException
    //   183	201	204	android/database/sqlite/SQLiteDatabaseCorruptException
    //   244	253	204	android/database/sqlite/SQLiteDatabaseCorruptException
    //   287	329	204	android/database/sqlite/SQLiteDatabaseCorruptException
    //   329	347	204	android/database/sqlite/SQLiteDatabaseCorruptException
    //   382	391	204	android/database/sqlite/SQLiteDatabaseCorruptException
    //   394	418	204	android/database/sqlite/SQLiteDatabaseCorruptException
    //   418	487	204	android/database/sqlite/SQLiteDatabaseCorruptException
    //   490	507	204	android/database/sqlite/SQLiteDatabaseCorruptException
    //   507	531	204	android/database/sqlite/SQLiteDatabaseCorruptException
    //   531	600	204	android/database/sqlite/SQLiteDatabaseCorruptException
    //   603	620	204	android/database/sqlite/SQLiteDatabaseCorruptException
    //   620	624	204	android/database/sqlite/SQLiteDatabaseCorruptException
    //   38	56	256	java/lang/Throwable
    //   56	119	256	java/lang/Throwable
    //   123	138	256	java/lang/Throwable
    //   141	183	256	java/lang/Throwable
    //   183	201	256	java/lang/Throwable
    //   244	253	256	java/lang/Throwable
    //   287	329	256	java/lang/Throwable
    //   329	347	256	java/lang/Throwable
    //   382	391	256	java/lang/Throwable
    //   394	418	256	java/lang/Throwable
    //   418	487	256	java/lang/Throwable
    //   490	507	256	java/lang/Throwable
    //   507	531	256	java/lang/Throwable
    //   531	600	256	java/lang/Throwable
    //   603	620	256	java/lang/Throwable
    //   620	624	256	java/lang/Throwable
    //   38	56	350	finally
    //   56	119	350	finally
    //   123	138	350	finally
    //   141	183	350	finally
    //   183	201	350	finally
    //   244	253	350	finally
    //   287	329	350	finally
    //   329	347	350	finally
    //   382	391	350	finally
    //   394	418	350	finally
    //   418	487	350	finally
    //   490	507	350	finally
    //   507	531	350	finally
    //   531	600	350	finally
    //   603	620	350	finally
    //   620	624	350	finally
    //   640	644	654	java/lang/Throwable
    //   230	234	658	java/lang/Throwable
    //   273	277	662	java/lang/Throwable
    //   367	371	666	java/lang/Throwable
    //   3	13	670	finally
    //   13	17	679	finally
    //   20	29	679	finally
    //   210	216	686	finally
    //   3	13	703	java/lang/Throwable
    //   13	17	712	java/lang/Throwable
    //   20	29	712	java/lang/Throwable
    //   3	13	719	android/database/sqlite/SQLiteDatabaseCorruptException
    //   13	17	728	android/database/sqlite/SQLiteDatabaseCorruptException
    //   20	29	728	android/database/sqlite/SQLiteDatabaseCorruptException
  }
  
  private void b()
  {
    int i = 0;
    try
    {
      if (TextUtils.isEmpty(d))
      {
        SharedPreferences localSharedPreferences = ba.a(c);
        Object localObject2 = localSharedPreferences.getString("ek__id", null);
        Object localObject1 = localObject2;
        if (TextUtils.isEmpty((CharSequence)localObject2))
        {
          localObject2 = bv.A(c);
          localObject1 = localObject2;
          if (!TextUtils.isEmpty((CharSequence)localObject2))
          {
            localSharedPreferences.edit().putString("ek__id", (String)localObject2).commit();
            localObject1 = localObject2;
          }
        }
        if (!TextUtils.isEmpty((CharSequence)localObject1))
        {
          localObject1 = ((String)localObject1).substring(1, 9);
          localObject2 = new StringBuilder();
        }
        for (;;)
        {
          if (i < ((String)localObject1).length())
          {
            char c1 = ((String)localObject1).charAt(i);
            if (Character.isDigit(c1))
            {
              if (Integer.parseInt(Character.toString(c1)) == 0) {
                ((StringBuilder)localObject2).append(0);
              } else {
                ((StringBuilder)localObject2).append(10 - Integer.parseInt(Character.toString(c1)));
              }
            }
            else {
              ((StringBuilder)localObject2).append(c1);
            }
          }
          else
          {
            d = ((StringBuilder)localObject2).toString();
            if (TextUtils.isEmpty(d)) {
              break;
            }
            d += new StringBuilder(d).reverse().toString();
            localObject1 = localSharedPreferences.getString("ek_key", null);
            if (TextUtils.isEmpty((CharSequence)localObject1))
            {
              localSharedPreferences.edit().putString("ek_key", a("umeng+")).commit();
              return;
            }
            if ("umeng+".equals(b((String)localObject1))) {
              break;
            }
            a(true, false);
            return;
          }
          i += 1;
        }
      }
      return;
    }
    catch (Throwable localThrowable) {}
  }
  
  /* Error */
  private void b(JSONObject paramJSONObject)
  {
    // Byte code:
    //   0: aconst_null
    //   1: astore 4
    //   3: aconst_null
    //   4: astore 6
    //   6: aconst_null
    //   7: astore 5
    //   9: aconst_null
    //   10: astore_3
    //   11: getstatic 35	com/umeng/analytics/pro/w:c	Landroid/content/Context;
    //   14: invokestatic 150	com/umeng/analytics/pro/u:a	(Landroid/content/Context;)Lcom/umeng/analytics/pro/u;
    //   17: invokevirtual 153	com/umeng/analytics/pro/u:a	()Landroid/database/sqlite/SQLiteDatabase;
    //   20: astore_2
    //   21: aload_3
    //   22: astore 4
    //   24: aload 5
    //   26: astore 6
    //   28: aload_2
    //   29: invokevirtual 156	android/database/sqlite/SQLiteDatabase:beginTransaction	()V
    //   32: goto +389 -> 421
    //   35: aload_3
    //   36: astore 4
    //   38: aload 5
    //   40: astore 6
    //   42: aload_2
    //   43: ldc_w 300
    //   46: aconst_null
    //   47: invokevirtual 95	android/database/sqlite/SQLiteDatabase:rawQuery	(Ljava/lang/String;[Ljava/lang/String;)Landroid/database/Cursor;
    //   50: astore_3
    //   51: aload_3
    //   52: ifnull +214 -> 266
    //   55: aload_3
    //   56: astore 4
    //   58: aload_3
    //   59: astore 5
    //   61: aload_2
    //   62: astore 7
    //   64: aload_3
    //   65: astore 6
    //   67: new 114	org/json/JSONArray
    //   70: dup
    //   71: invokespecial 115	org/json/JSONArray:<init>	()V
    //   74: astore 8
    //   76: aload_3
    //   77: astore 4
    //   79: aload_3
    //   80: astore 5
    //   82: aload_2
    //   83: astore 7
    //   85: aload_3
    //   86: astore 6
    //   88: aload_3
    //   89: invokeinterface 101 1 0
    //   94: ifeq +130 -> 224
    //   97: aload_3
    //   98: astore 4
    //   100: aload_3
    //   101: astore 5
    //   103: aload_2
    //   104: astore 7
    //   106: aload_3
    //   107: astore 6
    //   109: aload_3
    //   110: aload_3
    //   111: ldc_w 302
    //   114: invokeinterface 105 2 0
    //   119: invokeinterface 109 2 0
    //   124: astore 9
    //   126: aload_3
    //   127: astore 4
    //   129: aload_3
    //   130: astore 5
    //   132: aload_2
    //   133: astore 7
    //   135: aload_3
    //   136: astore 6
    //   138: aload 9
    //   140: invokestatic 121	android/text/TextUtils:isEmpty	(Ljava/lang/CharSequence;)Z
    //   143: ifne -67 -> 76
    //   146: aload_3
    //   147: astore 4
    //   149: aload_3
    //   150: astore 5
    //   152: aload_2
    //   153: astore 7
    //   155: aload_3
    //   156: astore 6
    //   158: aload 8
    //   160: new 160	org/json/JSONObject
    //   163: dup
    //   164: aload_0
    //   165: aload 9
    //   167: invokevirtual 112	com/umeng/analytics/pro/w:b	(Ljava/lang/String;)Ljava/lang/String;
    //   170: invokespecial 184	org/json/JSONObject:<init>	(Ljava/lang/String;)V
    //   173: invokevirtual 128	org/json/JSONArray:put	(Ljava/lang/Object;)Lorg/json/JSONArray;
    //   176: pop
    //   177: goto -101 -> 76
    //   180: astore_1
    //   181: aload 4
    //   183: astore 5
    //   185: aload_2
    //   186: astore 7
    //   188: getstatic 35	com/umeng/analytics/pro/w:c	Landroid/content/Context;
    //   191: invokestatic 200	com/umeng/analytics/pro/v:b	(Landroid/content/Context;)V
    //   194: aload 4
    //   196: ifnull +10 -> 206
    //   199: aload 4
    //   201: invokeinterface 141 1 0
    //   206: aload_2
    //   207: ifnull +7 -> 214
    //   210: aload_2
    //   211: invokevirtual 203	android/database/sqlite/SQLiteDatabase:endTransaction	()V
    //   214: getstatic 35	com/umeng/analytics/pro/w:c	Landroid/content/Context;
    //   217: invokestatic 150	com/umeng/analytics/pro/u:a	(Landroid/content/Context;)Lcom/umeng/analytics/pro/u;
    //   220: invokevirtual 204	com/umeng/analytics/pro/u:b	()V
    //   223: return
    //   224: aload_3
    //   225: astore 4
    //   227: aload_3
    //   228: astore 5
    //   230: aload_2
    //   231: astore 7
    //   233: aload_3
    //   234: astore 6
    //   236: aload 8
    //   238: invokevirtual 225	org/json/JSONArray:length	()I
    //   241: ifle +25 -> 266
    //   244: aload_3
    //   245: astore 4
    //   247: aload_3
    //   248: astore 5
    //   250: aload_2
    //   251: astore 7
    //   253: aload_3
    //   254: astore 6
    //   256: aload_1
    //   257: ldc_w 304
    //   260: aload 8
    //   262: invokevirtual 195	org/json/JSONObject:put	(Ljava/lang/String;Ljava/lang/Object;)Lorg/json/JSONObject;
    //   265: pop
    //   266: aload_3
    //   267: astore 4
    //   269: aload_3
    //   270: astore 5
    //   272: aload_2
    //   273: astore 7
    //   275: aload_3
    //   276: astore 6
    //   278: aload_2
    //   279: invokevirtual 232	android/database/sqlite/SQLiteDatabase:setTransactionSuccessful	()V
    //   282: aload_3
    //   283: ifnull +9 -> 292
    //   286: aload_3
    //   287: invokeinterface 141 1 0
    //   292: aload_2
    //   293: ifnull +7 -> 300
    //   296: aload_2
    //   297: invokevirtual 203	android/database/sqlite/SQLiteDatabase:endTransaction	()V
    //   300: getstatic 35	com/umeng/analytics/pro/w:c	Landroid/content/Context;
    //   303: invokestatic 150	com/umeng/analytics/pro/u:a	(Landroid/content/Context;)Lcom/umeng/analytics/pro/u;
    //   306: invokevirtual 204	com/umeng/analytics/pro/u:b	()V
    //   309: return
    //   310: astore_1
    //   311: aconst_null
    //   312: astore_2
    //   313: aload 6
    //   315: ifnull +10 -> 325
    //   318: aload 6
    //   320: invokeinterface 141 1 0
    //   325: aload_2
    //   326: ifnull +7 -> 333
    //   329: aload_2
    //   330: invokevirtual 203	android/database/sqlite/SQLiteDatabase:endTransaction	()V
    //   333: getstatic 35	com/umeng/analytics/pro/w:c	Landroid/content/Context;
    //   336: invokestatic 150	com/umeng/analytics/pro/u:a	(Landroid/content/Context;)Lcom/umeng/analytics/pro/u;
    //   339: invokevirtual 204	com/umeng/analytics/pro/u:b	()V
    //   342: return
    //   343: astore_1
    //   344: aconst_null
    //   345: astore_3
    //   346: aconst_null
    //   347: astore_2
    //   348: aload_2
    //   349: ifnull +9 -> 358
    //   352: aload_2
    //   353: invokeinterface 141 1 0
    //   358: aload_3
    //   359: ifnull +7 -> 366
    //   362: aload_3
    //   363: invokevirtual 203	android/database/sqlite/SQLiteDatabase:endTransaction	()V
    //   366: getstatic 35	com/umeng/analytics/pro/w:c	Landroid/content/Context;
    //   369: invokestatic 150	com/umeng/analytics/pro/u:a	(Landroid/content/Context;)Lcom/umeng/analytics/pro/u;
    //   372: invokevirtual 204	com/umeng/analytics/pro/u:b	()V
    //   375: aload_1
    //   376: athrow
    //   377: astore_1
    //   378: goto -78 -> 300
    //   381: astore_1
    //   382: goto -168 -> 214
    //   385: astore_1
    //   386: goto -53 -> 333
    //   389: astore_2
    //   390: goto -24 -> 366
    //   393: astore_1
    //   394: aload_2
    //   395: astore_3
    //   396: aconst_null
    //   397: astore_2
    //   398: goto -50 -> 348
    //   401: astore_1
    //   402: aload 7
    //   404: astore_3
    //   405: aload 5
    //   407: astore_2
    //   408: goto -60 -> 348
    //   411: astore_1
    //   412: goto -99 -> 313
    //   415: astore_1
    //   416: aconst_null
    //   417: astore_2
    //   418: goto -237 -> 181
    //   421: goto -386 -> 35
    // Local variable table:
    //   start	length	slot	name	signature
    //   0	424	0	this	w
    //   0	424	1	paramJSONObject	JSONObject
    //   20	333	2	localSQLiteDatabase1	android.database.sqlite.SQLiteDatabase
    //   389	6	2	localThrowable	Throwable
    //   397	21	2	localObject1	Object
    //   10	395	3	localObject2	Object
    //   1	267	4	localObject3	Object
    //   7	399	5	localObject4	Object
    //   4	315	6	localObject5	Object
    //   62	341	7	localSQLiteDatabase2	android.database.sqlite.SQLiteDatabase
    //   74	187	8	localJSONArray	org.json.JSONArray
    //   124	42	9	str	String
    // Exception table:
    //   from	to	target	type
    //   28	32	180	android/database/sqlite/SQLiteDatabaseCorruptException
    //   42	51	180	android/database/sqlite/SQLiteDatabaseCorruptException
    //   67	76	180	android/database/sqlite/SQLiteDatabaseCorruptException
    //   88	97	180	android/database/sqlite/SQLiteDatabaseCorruptException
    //   109	126	180	android/database/sqlite/SQLiteDatabaseCorruptException
    //   138	146	180	android/database/sqlite/SQLiteDatabaseCorruptException
    //   158	177	180	android/database/sqlite/SQLiteDatabaseCorruptException
    //   236	244	180	android/database/sqlite/SQLiteDatabaseCorruptException
    //   256	266	180	android/database/sqlite/SQLiteDatabaseCorruptException
    //   278	282	180	android/database/sqlite/SQLiteDatabaseCorruptException
    //   11	21	310	java/lang/Throwable
    //   11	21	343	finally
    //   296	300	377	java/lang/Throwable
    //   210	214	381	java/lang/Throwable
    //   329	333	385	java/lang/Throwable
    //   362	366	389	java/lang/Throwable
    //   28	32	393	finally
    //   42	51	393	finally
    //   67	76	401	finally
    //   88	97	401	finally
    //   109	126	401	finally
    //   138	146	401	finally
    //   158	177	401	finally
    //   188	194	401	finally
    //   236	244	401	finally
    //   256	266	401	finally
    //   278	282	401	finally
    //   28	32	411	java/lang/Throwable
    //   42	51	411	java/lang/Throwable
    //   67	76	411	java/lang/Throwable
    //   88	97	411	java/lang/Throwable
    //   109	126	411	java/lang/Throwable
    //   138	146	411	java/lang/Throwable
    //   158	177	411	java/lang/Throwable
    //   236	244	411	java/lang/Throwable
    //   256	266	411	java/lang/Throwable
    //   278	282	411	java/lang/Throwable
    //   11	21	415	android/database/sqlite/SQLiteDatabaseCorruptException
  }
  
  /* Error */
  private void c(JSONObject paramJSONObject)
  {
    // Byte code:
    //   0: aconst_null
    //   1: astore 13
    //   3: aconst_null
    //   4: astore 9
    //   6: aconst_null
    //   7: astore 10
    //   9: aconst_null
    //   10: astore 7
    //   12: aload 7
    //   14: astore 8
    //   16: aload 10
    //   18: astore 12
    //   20: getstatic 35	com/umeng/analytics/pro/w:c	Landroid/content/Context;
    //   23: invokestatic 150	com/umeng/analytics/pro/u:a	(Landroid/content/Context;)Lcom/umeng/analytics/pro/u;
    //   26: invokevirtual 153	com/umeng/analytics/pro/u:a	()Landroid/database/sqlite/SQLiteDatabase;
    //   29: astore 6
    //   31: aload 7
    //   33: astore 8
    //   35: aload 6
    //   37: astore 9
    //   39: aload 10
    //   41: astore 12
    //   43: aload 6
    //   45: astore 13
    //   47: aload 6
    //   49: invokevirtual 156	android/database/sqlite/SQLiteDatabase:beginTransaction	()V
    //   52: goto +1462 -> 1514
    //   55: aload 7
    //   57: astore 8
    //   59: aload 6
    //   61: astore 9
    //   63: aload 10
    //   65: astore 12
    //   67: aload 6
    //   69: astore 13
    //   71: aload 6
    //   73: ldc_w 306
    //   76: aconst_null
    //   77: invokevirtual 95	android/database/sqlite/SQLiteDatabase:rawQuery	(Ljava/lang/String;[Ljava/lang/String;)Landroid/database/Cursor;
    //   80: astore 7
    //   82: aload 7
    //   84: ifnull +1256 -> 1340
    //   87: aload 7
    //   89: astore 8
    //   91: aload 6
    //   93: astore 9
    //   95: aload 7
    //   97: astore 12
    //   99: aload 6
    //   101: astore 13
    //   103: aload 7
    //   105: astore 10
    //   107: aload 6
    //   109: astore 11
    //   111: new 114	org/json/JSONArray
    //   114: dup
    //   115: invokespecial 115	org/json/JSONArray:<init>	()V
    //   118: astore 14
    //   120: aload 7
    //   122: astore 8
    //   124: aload 6
    //   126: astore 9
    //   128: aload 7
    //   130: astore 12
    //   132: aload 6
    //   134: astore 13
    //   136: aload 7
    //   138: astore 10
    //   140: aload 6
    //   142: astore 11
    //   144: aload_0
    //   145: getfield 46	com/umeng/analytics/pro/w:h	Ljava/util/List;
    //   148: invokeinterface 53 1 0
    //   153: aload 7
    //   155: astore 8
    //   157: aload 6
    //   159: astore 9
    //   161: aload 7
    //   163: astore 12
    //   165: aload 6
    //   167: astore 13
    //   169: aload 7
    //   171: astore 10
    //   173: aload 6
    //   175: astore 11
    //   177: aload 7
    //   179: invokeinterface 101 1 0
    //   184: ifeq +1090 -> 1274
    //   187: aload 7
    //   189: astore 8
    //   191: aload 6
    //   193: astore 9
    //   195: aload 7
    //   197: astore 12
    //   199: aload 6
    //   201: astore 13
    //   203: aload 7
    //   205: astore 10
    //   207: aload 6
    //   209: astore 11
    //   211: new 160	org/json/JSONObject
    //   214: dup
    //   215: invokespecial 161	org/json/JSONObject:<init>	()V
    //   218: astore 15
    //   220: aload 7
    //   222: astore 8
    //   224: aload 6
    //   226: astore 9
    //   228: aload 7
    //   230: astore 12
    //   232: aload 6
    //   234: astore 13
    //   236: aload 7
    //   238: astore 10
    //   240: aload 6
    //   242: astore 11
    //   244: aload 7
    //   246: aload 7
    //   248: ldc_w 308
    //   251: invokeinterface 105 2 0
    //   256: invokeinterface 109 2 0
    //   261: astore 16
    //   263: aload 7
    //   265: astore 8
    //   267: aload 6
    //   269: astore 9
    //   271: aload 7
    //   273: astore 12
    //   275: aload 6
    //   277: astore 13
    //   279: aload 7
    //   281: astore 10
    //   283: aload 6
    //   285: astore 11
    //   287: aload 7
    //   289: aload 7
    //   291: ldc_w 310
    //   294: invokeinterface 105 2 0
    //   299: invokeinterface 109 2 0
    //   304: astore 17
    //   306: aload 7
    //   308: astore 8
    //   310: aload 6
    //   312: astore 9
    //   314: aload 7
    //   316: astore 12
    //   318: aload 6
    //   320: astore 13
    //   322: aload 7
    //   324: astore 10
    //   326: aload 6
    //   328: astore 11
    //   330: aload 16
    //   332: invokestatic 121	android/text/TextUtils:isEmpty	(Ljava/lang/CharSequence;)Z
    //   335: ifne -182 -> 153
    //   338: aload 7
    //   340: astore 8
    //   342: aload 6
    //   344: astore 9
    //   346: aload 7
    //   348: astore 12
    //   350: aload 6
    //   352: astore 13
    //   354: aload 7
    //   356: astore 10
    //   358: aload 6
    //   360: astore 11
    //   362: aload 17
    //   364: invokestatic 121	android/text/TextUtils:isEmpty	(Ljava/lang/CharSequence;)Z
    //   367: ifne -214 -> 153
    //   370: aload 7
    //   372: astore 8
    //   374: aload 6
    //   376: astore 9
    //   378: aload 7
    //   380: astore 12
    //   382: aload 6
    //   384: astore 13
    //   386: aload 7
    //   388: astore 10
    //   390: aload 6
    //   392: astore 11
    //   394: aload 16
    //   396: invokestatic 316	java/lang/Long:parseLong	(Ljava/lang/String;)J
    //   399: lstore_2
    //   400: aload 7
    //   402: astore 8
    //   404: aload 6
    //   406: astore 9
    //   408: aload 7
    //   410: astore 12
    //   412: aload 6
    //   414: astore 13
    //   416: aload 7
    //   418: astore 10
    //   420: aload 6
    //   422: astore 11
    //   424: aload 17
    //   426: invokestatic 316	java/lang/Long:parseLong	(Ljava/lang/String;)J
    //   429: lstore 4
    //   431: goto +1086 -> 1517
    //   434: aload 7
    //   436: astore 8
    //   438: aload 6
    //   440: astore 9
    //   442: aload 7
    //   444: astore 12
    //   446: aload 6
    //   448: astore 13
    //   450: aload 7
    //   452: astore 10
    //   454: aload 6
    //   456: astore 11
    //   458: aload 7
    //   460: aload 7
    //   462: ldc_w 302
    //   465: invokeinterface 105 2 0
    //   470: invokeinterface 109 2 0
    //   475: astore 18
    //   477: goto +1052 -> 1529
    //   480: aload 7
    //   482: astore 8
    //   484: aload 6
    //   486: astore 9
    //   488: aload 7
    //   490: astore 12
    //   492: aload 6
    //   494: astore 13
    //   496: aload 7
    //   498: astore 10
    //   500: aload 6
    //   502: astore 11
    //   504: aload 7
    //   506: aload 7
    //   508: ldc_w 318
    //   511: invokeinterface 105 2 0
    //   516: invokeinterface 109 2 0
    //   521: astore 19
    //   523: goto +1009 -> 1532
    //   526: aload 7
    //   528: astore 8
    //   530: aload 6
    //   532: astore 9
    //   534: aload 7
    //   536: astore 12
    //   538: aload 6
    //   540: astore 13
    //   542: aload 7
    //   544: astore 10
    //   546: aload 6
    //   548: astore 11
    //   550: aload 7
    //   552: aload 7
    //   554: ldc_w 320
    //   557: invokeinterface 105 2 0
    //   562: invokeinterface 109 2 0
    //   567: astore 20
    //   569: goto +966 -> 1535
    //   572: aload 7
    //   574: astore 8
    //   576: aload 6
    //   578: astore 9
    //   580: aload 7
    //   582: astore 12
    //   584: aload 6
    //   586: astore 13
    //   588: aload 7
    //   590: astore 10
    //   592: aload 6
    //   594: astore 11
    //   596: aload 7
    //   598: aload 7
    //   600: ldc_w 322
    //   603: invokeinterface 105 2 0
    //   608: invokeinterface 109 2 0
    //   613: astore 21
    //   615: goto +923 -> 1538
    //   618: aload 7
    //   620: astore 8
    //   622: aload 6
    //   624: astore 9
    //   626: aload 7
    //   628: astore 12
    //   630: aload 6
    //   632: astore 13
    //   634: aload 7
    //   636: astore 10
    //   638: aload 6
    //   640: astore 11
    //   642: aload 7
    //   644: aload 7
    //   646: ldc 81
    //   648: invokeinterface 105 2 0
    //   653: invokeinterface 109 2 0
    //   658: astore 22
    //   660: aload 7
    //   662: astore 8
    //   664: aload 6
    //   666: astore 9
    //   668: aload 7
    //   670: astore 12
    //   672: aload 6
    //   674: astore 13
    //   676: aload 7
    //   678: astore 10
    //   680: aload 6
    //   682: astore 11
    //   684: aload_0
    //   685: getfield 46	com/umeng/analytics/pro/w:h	Ljava/util/List;
    //   688: aload 22
    //   690: invokeinterface 325 2 0
    //   695: pop
    //   696: aload 7
    //   698: astore 8
    //   700: aload 6
    //   702: astore 9
    //   704: aload 7
    //   706: astore 12
    //   708: aload 6
    //   710: astore 13
    //   712: aload 7
    //   714: astore 10
    //   716: aload 6
    //   718: astore 11
    //   720: aload 15
    //   722: ldc_w 327
    //   725: aload 22
    //   727: invokevirtual 195	org/json/JSONObject:put	(Ljava/lang/String;Ljava/lang/Object;)Lorg/json/JSONObject;
    //   730: pop
    //   731: aload 7
    //   733: astore 8
    //   735: aload 6
    //   737: astore 9
    //   739: aload 7
    //   741: astore 12
    //   743: aload 6
    //   745: astore 13
    //   747: aload 7
    //   749: astore 10
    //   751: aload 6
    //   753: astore 11
    //   755: aload 15
    //   757: ldc_w 329
    //   760: aload 17
    //   762: invokevirtual 195	org/json/JSONObject:put	(Ljava/lang/String;Ljava/lang/Object;)Lorg/json/JSONObject;
    //   765: pop
    //   766: aload 7
    //   768: astore 8
    //   770: aload 6
    //   772: astore 9
    //   774: aload 7
    //   776: astore 12
    //   778: aload 6
    //   780: astore 13
    //   782: aload 7
    //   784: astore 10
    //   786: aload 6
    //   788: astore 11
    //   790: aload 15
    //   792: ldc_w 331
    //   795: aload 16
    //   797: invokevirtual 195	org/json/JSONObject:put	(Ljava/lang/String;Ljava/lang/Object;)Lorg/json/JSONObject;
    //   800: pop
    //   801: goto +740 -> 1541
    //   804: aload 7
    //   806: astore 8
    //   808: aload 6
    //   810: astore 9
    //   812: aload 7
    //   814: astore 12
    //   816: aload 6
    //   818: astore 13
    //   820: aload 7
    //   822: astore 10
    //   824: aload 6
    //   826: astore 11
    //   828: aload 15
    //   830: ldc_w 333
    //   833: aload 16
    //   835: invokestatic 316	java/lang/Long:parseLong	(Ljava/lang/String;)J
    //   838: aload 17
    //   840: invokestatic 316	java/lang/Long:parseLong	(Ljava/lang/String;)J
    //   843: lsub
    //   844: invokevirtual 336	org/json/JSONObject:put	(Ljava/lang/String;J)Lorg/json/JSONObject;
    //   847: pop
    //   848: aload 7
    //   850: astore 8
    //   852: aload 6
    //   854: astore 9
    //   856: aload 7
    //   858: astore 12
    //   860: aload 6
    //   862: astore 13
    //   864: aload 7
    //   866: astore 10
    //   868: aload 6
    //   870: astore 11
    //   872: aload 18
    //   874: invokestatic 121	android/text/TextUtils:isEmpty	(Ljava/lang/CharSequence;)Z
    //   877: ifne +49 -> 926
    //   880: aload 7
    //   882: astore 8
    //   884: aload 6
    //   886: astore 9
    //   888: aload 7
    //   890: astore 12
    //   892: aload 6
    //   894: astore 13
    //   896: aload 7
    //   898: astore 10
    //   900: aload 6
    //   902: astore 11
    //   904: aload 15
    //   906: ldc_w 338
    //   909: new 114	org/json/JSONArray
    //   912: dup
    //   913: aload_0
    //   914: aload 18
    //   916: invokevirtual 112	com/umeng/analytics/pro/w:b	(Ljava/lang/String;)Ljava/lang/String;
    //   919: invokespecial 124	org/json/JSONArray:<init>	(Ljava/lang/String;)V
    //   922: invokevirtual 195	org/json/JSONObject:put	(Ljava/lang/String;Ljava/lang/Object;)Lorg/json/JSONObject;
    //   925: pop
    //   926: aload 7
    //   928: astore 8
    //   930: aload 6
    //   932: astore 9
    //   934: aload 7
    //   936: astore 12
    //   938: aload 6
    //   940: astore 13
    //   942: aload 7
    //   944: astore 10
    //   946: aload 6
    //   948: astore 11
    //   950: aload 19
    //   952: invokestatic 121	android/text/TextUtils:isEmpty	(Ljava/lang/CharSequence;)Z
    //   955: ifne +49 -> 1004
    //   958: aload 7
    //   960: astore 8
    //   962: aload 6
    //   964: astore 9
    //   966: aload 7
    //   968: astore 12
    //   970: aload 6
    //   972: astore 13
    //   974: aload 7
    //   976: astore 10
    //   978: aload 6
    //   980: astore 11
    //   982: aload 15
    //   984: ldc_w 340
    //   987: new 114	org/json/JSONArray
    //   990: dup
    //   991: aload_0
    //   992: aload 19
    //   994: invokevirtual 112	com/umeng/analytics/pro/w:b	(Ljava/lang/String;)Ljava/lang/String;
    //   997: invokespecial 124	org/json/JSONArray:<init>	(Ljava/lang/String;)V
    //   1000: invokevirtual 195	org/json/JSONObject:put	(Ljava/lang/String;Ljava/lang/Object;)Lorg/json/JSONObject;
    //   1003: pop
    //   1004: aload 7
    //   1006: astore 8
    //   1008: aload 6
    //   1010: astore 9
    //   1012: aload 7
    //   1014: astore 12
    //   1016: aload 6
    //   1018: astore 13
    //   1020: aload 7
    //   1022: astore 10
    //   1024: aload 6
    //   1026: astore 11
    //   1028: aload 20
    //   1030: invokestatic 121	android/text/TextUtils:isEmpty	(Ljava/lang/CharSequence;)Z
    //   1033: ifne +49 -> 1082
    //   1036: aload 7
    //   1038: astore 8
    //   1040: aload 6
    //   1042: astore 9
    //   1044: aload 7
    //   1046: astore 12
    //   1048: aload 6
    //   1050: astore 13
    //   1052: aload 7
    //   1054: astore 10
    //   1056: aload 6
    //   1058: astore 11
    //   1060: aload 15
    //   1062: ldc_w 342
    //   1065: new 160	org/json/JSONObject
    //   1068: dup
    //   1069: aload_0
    //   1070: aload 20
    //   1072: invokevirtual 112	com/umeng/analytics/pro/w:b	(Ljava/lang/String;)Ljava/lang/String;
    //   1075: invokespecial 184	org/json/JSONObject:<init>	(Ljava/lang/String;)V
    //   1078: invokevirtual 195	org/json/JSONObject:put	(Ljava/lang/String;Ljava/lang/Object;)Lorg/json/JSONObject;
    //   1081: pop
    //   1082: aload 7
    //   1084: astore 8
    //   1086: aload 6
    //   1088: astore 9
    //   1090: aload 7
    //   1092: astore 12
    //   1094: aload 6
    //   1096: astore 13
    //   1098: aload 7
    //   1100: astore 10
    //   1102: aload 6
    //   1104: astore 11
    //   1106: aload 21
    //   1108: invokestatic 121	android/text/TextUtils:isEmpty	(Ljava/lang/CharSequence;)Z
    //   1111: ifne +49 -> 1160
    //   1114: aload 7
    //   1116: astore 8
    //   1118: aload 6
    //   1120: astore 9
    //   1122: aload 7
    //   1124: astore 12
    //   1126: aload 6
    //   1128: astore 13
    //   1130: aload 7
    //   1132: astore 10
    //   1134: aload 6
    //   1136: astore 11
    //   1138: aload 15
    //   1140: ldc_w 344
    //   1143: new 114	org/json/JSONArray
    //   1146: dup
    //   1147: aload_0
    //   1148: aload 21
    //   1150: invokevirtual 112	com/umeng/analytics/pro/w:b	(Ljava/lang/String;)Ljava/lang/String;
    //   1153: invokespecial 124	org/json/JSONArray:<init>	(Ljava/lang/String;)V
    //   1156: invokevirtual 195	org/json/JSONObject:put	(Ljava/lang/String;Ljava/lang/Object;)Lorg/json/JSONObject;
    //   1159: pop
    //   1160: aload 7
    //   1162: astore 8
    //   1164: aload 6
    //   1166: astore 9
    //   1168: aload 7
    //   1170: astore 12
    //   1172: aload 6
    //   1174: astore 13
    //   1176: aload 7
    //   1178: astore 10
    //   1180: aload 6
    //   1182: astore 11
    //   1184: aload 15
    //   1186: invokevirtual 208	org/json/JSONObject:length	()I
    //   1189: ifle -1036 -> 153
    //   1192: aload 7
    //   1194: astore 8
    //   1196: aload 6
    //   1198: astore 9
    //   1200: aload 7
    //   1202: astore 12
    //   1204: aload 6
    //   1206: astore 13
    //   1208: aload 7
    //   1210: astore 10
    //   1212: aload 6
    //   1214: astore 11
    //   1216: aload 14
    //   1218: aload 15
    //   1220: invokevirtual 128	org/json/JSONArray:put	(Ljava/lang/Object;)Lorg/json/JSONArray;
    //   1223: pop
    //   1224: goto -1071 -> 153
    //   1227: astore_1
    //   1228: aload 8
    //   1230: astore 10
    //   1232: aload 9
    //   1234: astore 11
    //   1236: getstatic 35	com/umeng/analytics/pro/w:c	Landroid/content/Context;
    //   1239: invokestatic 200	com/umeng/analytics/pro/v:b	(Landroid/content/Context;)V
    //   1242: aload 8
    //   1244: ifnull +10 -> 1254
    //   1247: aload 8
    //   1249: invokeinterface 141 1 0
    //   1254: aload 9
    //   1256: ifnull +8 -> 1264
    //   1259: aload 9
    //   1261: invokevirtual 203	android/database/sqlite/SQLiteDatabase:endTransaction	()V
    //   1264: getstatic 35	com/umeng/analytics/pro/w:c	Landroid/content/Context;
    //   1267: invokestatic 150	com/umeng/analytics/pro/u:a	(Landroid/content/Context;)Lcom/umeng/analytics/pro/u;
    //   1270: invokevirtual 204	com/umeng/analytics/pro/u:b	()V
    //   1273: return
    //   1274: aload 7
    //   1276: astore 8
    //   1278: aload 6
    //   1280: astore 9
    //   1282: aload 7
    //   1284: astore 12
    //   1286: aload 6
    //   1288: astore 13
    //   1290: aload 7
    //   1292: astore 10
    //   1294: aload 6
    //   1296: astore 11
    //   1298: aload 14
    //   1300: invokevirtual 225	org/json/JSONArray:length	()I
    //   1303: ifle +37 -> 1340
    //   1306: aload 7
    //   1308: astore 8
    //   1310: aload 6
    //   1312: astore 9
    //   1314: aload 7
    //   1316: astore 12
    //   1318: aload 6
    //   1320: astore 13
    //   1322: aload 7
    //   1324: astore 10
    //   1326: aload 6
    //   1328: astore 11
    //   1330: aload_1
    //   1331: ldc_w 346
    //   1334: aload 14
    //   1336: invokevirtual 195	org/json/JSONObject:put	(Ljava/lang/String;Ljava/lang/Object;)Lorg/json/JSONObject;
    //   1339: pop
    //   1340: aload 7
    //   1342: astore 8
    //   1344: aload 6
    //   1346: astore 9
    //   1348: aload 7
    //   1350: astore 12
    //   1352: aload 6
    //   1354: astore 13
    //   1356: aload 7
    //   1358: astore 10
    //   1360: aload 6
    //   1362: astore 11
    //   1364: aload 6
    //   1366: invokevirtual 232	android/database/sqlite/SQLiteDatabase:setTransactionSuccessful	()V
    //   1369: aload 7
    //   1371: ifnull +10 -> 1381
    //   1374: aload 7
    //   1376: invokeinterface 141 1 0
    //   1381: aload 6
    //   1383: ifnull +8 -> 1391
    //   1386: aload 6
    //   1388: invokevirtual 203	android/database/sqlite/SQLiteDatabase:endTransaction	()V
    //   1391: getstatic 35	com/umeng/analytics/pro/w:c	Landroid/content/Context;
    //   1394: invokestatic 150	com/umeng/analytics/pro/u:a	(Landroid/content/Context;)Lcom/umeng/analytics/pro/u;
    //   1397: invokevirtual 204	com/umeng/analytics/pro/u:b	()V
    //   1400: return
    //   1401: astore_1
    //   1402: aload 12
    //   1404: ifnull +10 -> 1414
    //   1407: aload 12
    //   1409: invokeinterface 141 1 0
    //   1414: aload 13
    //   1416: ifnull +8 -> 1424
    //   1419: aload 13
    //   1421: invokevirtual 203	android/database/sqlite/SQLiteDatabase:endTransaction	()V
    //   1424: getstatic 35	com/umeng/analytics/pro/w:c	Landroid/content/Context;
    //   1427: invokestatic 150	com/umeng/analytics/pro/u:a	(Landroid/content/Context;)Lcom/umeng/analytics/pro/u;
    //   1430: invokevirtual 204	com/umeng/analytics/pro/u:b	()V
    //   1433: return
    //   1434: astore_1
    //   1435: aconst_null
    //   1436: astore 7
    //   1438: aconst_null
    //   1439: astore 6
    //   1441: aload 6
    //   1443: ifnull +10 -> 1453
    //   1446: aload 6
    //   1448: invokeinterface 141 1 0
    //   1453: aload 7
    //   1455: ifnull +8 -> 1463
    //   1458: aload 7
    //   1460: invokevirtual 203	android/database/sqlite/SQLiteDatabase:endTransaction	()V
    //   1463: getstatic 35	com/umeng/analytics/pro/w:c	Landroid/content/Context;
    //   1466: invokestatic 150	com/umeng/analytics/pro/u:a	(Landroid/content/Context;)Lcom/umeng/analytics/pro/u;
    //   1469: invokevirtual 204	com/umeng/analytics/pro/u:b	()V
    //   1472: aload_1
    //   1473: athrow
    //   1474: astore_1
    //   1475: goto -84 -> 1391
    //   1478: astore_1
    //   1479: goto -215 -> 1264
    //   1482: astore_1
    //   1483: goto -59 -> 1424
    //   1486: astore 6
    //   1488: goto -25 -> 1463
    //   1491: astore_1
    //   1492: aload 6
    //   1494: astore 7
    //   1496: aconst_null
    //   1497: astore 6
    //   1499: goto -58 -> 1441
    //   1502: astore_1
    //   1503: aload 11
    //   1505: astore 7
    //   1507: aload 10
    //   1509: astore 6
    //   1511: goto -70 -> 1441
    //   1514: goto -1459 -> 55
    //   1517: lload_2
    //   1518: lload 4
    //   1520: lsub
    //   1521: lconst_0
    //   1522: lcmp
    //   1523: ifle -1370 -> 153
    //   1526: goto -1092 -> 434
    //   1529: goto -1049 -> 480
    //   1532: goto -1006 -> 526
    //   1535: goto -963 -> 572
    //   1538: goto -920 -> 618
    //   1541: goto -737 -> 804
    // Local variable table:
    //   start	length	slot	name	signature
    //   0	1544	0	this	w
    //   0	1544	1	paramJSONObject	JSONObject
    //   399	1119	2	l1	long
    //   429	1090	4	l2	long
    //   29	1418	6	localSQLiteDatabase	android.database.sqlite.SQLiteDatabase
    //   1486	7	6	localThrowable	Throwable
    //   1497	13	6	localObject1	Object
    //   10	1496	7	localObject2	Object
    //   14	1329	8	localObject3	Object
    //   4	1343	9	localObject4	Object
    //   7	1501	10	localObject5	Object
    //   109	1395	11	localObject6	Object
    //   18	1390	12	localObject7	Object
    //   1	1419	13	localObject8	Object
    //   118	1217	14	localJSONArray	org.json.JSONArray
    //   218	1001	15	localJSONObject	JSONObject
    //   261	573	16	str1	String
    //   304	535	17	str2	String
    //   475	440	18	str3	String
    //   521	472	19	str4	String
    //   567	504	20	str5	String
    //   613	536	21	str6	String
    //   658	68	22	str7	String
    // Exception table:
    //   from	to	target	type
    //   20	31	1227	android/database/sqlite/SQLiteDatabaseCorruptException
    //   47	52	1227	android/database/sqlite/SQLiteDatabaseCorruptException
    //   71	82	1227	android/database/sqlite/SQLiteDatabaseCorruptException
    //   111	120	1227	android/database/sqlite/SQLiteDatabaseCorruptException
    //   144	153	1227	android/database/sqlite/SQLiteDatabaseCorruptException
    //   177	187	1227	android/database/sqlite/SQLiteDatabaseCorruptException
    //   211	220	1227	android/database/sqlite/SQLiteDatabaseCorruptException
    //   244	263	1227	android/database/sqlite/SQLiteDatabaseCorruptException
    //   287	306	1227	android/database/sqlite/SQLiteDatabaseCorruptException
    //   330	338	1227	android/database/sqlite/SQLiteDatabaseCorruptException
    //   362	370	1227	android/database/sqlite/SQLiteDatabaseCorruptException
    //   394	400	1227	android/database/sqlite/SQLiteDatabaseCorruptException
    //   424	431	1227	android/database/sqlite/SQLiteDatabaseCorruptException
    //   458	477	1227	android/database/sqlite/SQLiteDatabaseCorruptException
    //   504	523	1227	android/database/sqlite/SQLiteDatabaseCorruptException
    //   550	569	1227	android/database/sqlite/SQLiteDatabaseCorruptException
    //   596	615	1227	android/database/sqlite/SQLiteDatabaseCorruptException
    //   642	660	1227	android/database/sqlite/SQLiteDatabaseCorruptException
    //   684	696	1227	android/database/sqlite/SQLiteDatabaseCorruptException
    //   720	731	1227	android/database/sqlite/SQLiteDatabaseCorruptException
    //   755	766	1227	android/database/sqlite/SQLiteDatabaseCorruptException
    //   790	801	1227	android/database/sqlite/SQLiteDatabaseCorruptException
    //   828	848	1227	android/database/sqlite/SQLiteDatabaseCorruptException
    //   872	880	1227	android/database/sqlite/SQLiteDatabaseCorruptException
    //   904	926	1227	android/database/sqlite/SQLiteDatabaseCorruptException
    //   950	958	1227	android/database/sqlite/SQLiteDatabaseCorruptException
    //   982	1004	1227	android/database/sqlite/SQLiteDatabaseCorruptException
    //   1028	1036	1227	android/database/sqlite/SQLiteDatabaseCorruptException
    //   1060	1082	1227	android/database/sqlite/SQLiteDatabaseCorruptException
    //   1106	1114	1227	android/database/sqlite/SQLiteDatabaseCorruptException
    //   1138	1160	1227	android/database/sqlite/SQLiteDatabaseCorruptException
    //   1184	1192	1227	android/database/sqlite/SQLiteDatabaseCorruptException
    //   1216	1224	1227	android/database/sqlite/SQLiteDatabaseCorruptException
    //   1298	1306	1227	android/database/sqlite/SQLiteDatabaseCorruptException
    //   1330	1340	1227	android/database/sqlite/SQLiteDatabaseCorruptException
    //   1364	1369	1227	android/database/sqlite/SQLiteDatabaseCorruptException
    //   20	31	1401	java/lang/Throwable
    //   47	52	1401	java/lang/Throwable
    //   71	82	1401	java/lang/Throwable
    //   111	120	1401	java/lang/Throwable
    //   144	153	1401	java/lang/Throwable
    //   177	187	1401	java/lang/Throwable
    //   211	220	1401	java/lang/Throwable
    //   244	263	1401	java/lang/Throwable
    //   287	306	1401	java/lang/Throwable
    //   330	338	1401	java/lang/Throwable
    //   362	370	1401	java/lang/Throwable
    //   394	400	1401	java/lang/Throwable
    //   424	431	1401	java/lang/Throwable
    //   458	477	1401	java/lang/Throwable
    //   504	523	1401	java/lang/Throwable
    //   550	569	1401	java/lang/Throwable
    //   596	615	1401	java/lang/Throwable
    //   642	660	1401	java/lang/Throwable
    //   684	696	1401	java/lang/Throwable
    //   720	731	1401	java/lang/Throwable
    //   755	766	1401	java/lang/Throwable
    //   790	801	1401	java/lang/Throwable
    //   828	848	1401	java/lang/Throwable
    //   872	880	1401	java/lang/Throwable
    //   904	926	1401	java/lang/Throwable
    //   950	958	1401	java/lang/Throwable
    //   982	1004	1401	java/lang/Throwable
    //   1028	1036	1401	java/lang/Throwable
    //   1060	1082	1401	java/lang/Throwable
    //   1106	1114	1401	java/lang/Throwable
    //   1138	1160	1401	java/lang/Throwable
    //   1184	1192	1401	java/lang/Throwable
    //   1216	1224	1401	java/lang/Throwable
    //   1298	1306	1401	java/lang/Throwable
    //   1330	1340	1401	java/lang/Throwable
    //   1364	1369	1401	java/lang/Throwable
    //   20	31	1434	finally
    //   1386	1391	1474	java/lang/Throwable
    //   1259	1264	1478	java/lang/Throwable
    //   1419	1424	1482	java/lang/Throwable
    //   1458	1463	1486	java/lang/Throwable
    //   47	52	1491	finally
    //   71	82	1491	finally
    //   111	120	1502	finally
    //   144	153	1502	finally
    //   177	187	1502	finally
    //   211	220	1502	finally
    //   244	263	1502	finally
    //   287	306	1502	finally
    //   330	338	1502	finally
    //   362	370	1502	finally
    //   394	400	1502	finally
    //   424	431	1502	finally
    //   458	477	1502	finally
    //   504	523	1502	finally
    //   550	569	1502	finally
    //   596	615	1502	finally
    //   642	660	1502	finally
    //   684	696	1502	finally
    //   720	731	1502	finally
    //   755	766	1502	finally
    //   790	801	1502	finally
    //   828	848	1502	finally
    //   872	880	1502	finally
    //   904	926	1502	finally
    //   950	958	1502	finally
    //   982	1004	1502	finally
    //   1028	1036	1502	finally
    //   1060	1082	1502	finally
    //   1106	1114	1502	finally
    //   1138	1160	1502	finally
    //   1184	1192	1502	finally
    //   1216	1224	1502	finally
    //   1236	1242	1502	finally
    //   1298	1306	1502	finally
    //   1330	1340	1502	finally
    //   1364	1369	1502	finally
  }
  
  public String a(String paramString)
  {
    try
    {
      if (TextUtils.isEmpty(d)) {
        return paramString;
      }
      paramString = Base64.encodeToString(bt.a(paramString.getBytes(), d.getBytes()), 0);
      return paramString;
    }
    catch (Exception paramString) {}
    return null;
  }
  
  public JSONObject a()
  {
    JSONObject localJSONObject1 = new JSONObject();
    JSONObject localJSONObject2 = new JSONObject();
    c(localJSONObject2);
    b(localJSONObject2);
    a(localJSONObject2);
    try
    {
      if (localJSONObject2.length() > 0) {
        localJSONObject1.put("body", localJSONObject2);
      }
      return localJSONObject1;
    }
    catch (Throwable localThrowable) {}
    return localJSONObject1;
  }
  
  /* Error */
  public void a(org.json.JSONArray paramJSONArray)
  {
    // Byte code:
    //   0: aconst_null
    //   1: astore 8
    //   3: aconst_null
    //   4: astore 5
    //   6: getstatic 35	com/umeng/analytics/pro/w:c	Landroid/content/Context;
    //   9: invokestatic 150	com/umeng/analytics/pro/u:a	(Landroid/content/Context;)Lcom/umeng/analytics/pro/u;
    //   12: invokevirtual 153	com/umeng/analytics/pro/u:a	()Landroid/database/sqlite/SQLiteDatabase;
    //   15: astore 4
    //   17: aload 4
    //   19: astore 5
    //   21: aload 4
    //   23: astore 8
    //   25: aload 4
    //   27: astore 6
    //   29: aload 4
    //   31: invokevirtual 156	android/database/sqlite/SQLiteDatabase:beginTransaction	()V
    //   34: goto +477 -> 511
    //   37: aload 4
    //   39: astore 5
    //   41: aload 4
    //   43: astore 8
    //   45: aload 4
    //   47: astore 6
    //   49: aload_1
    //   50: invokevirtual 225	org/json/JSONArray:length	()I
    //   53: istore_3
    //   54: iload_2
    //   55: iload_3
    //   56: if_icmpge +315 -> 371
    //   59: aload 4
    //   61: astore 5
    //   63: aload 4
    //   65: astore 8
    //   67: aload 4
    //   69: astore 6
    //   71: aload_1
    //   72: iload_2
    //   73: invokevirtual 377	org/json/JSONArray:getJSONObject	(I)Lorg/json/JSONObject;
    //   76: astore 10
    //   78: aload 4
    //   80: astore 5
    //   82: aload 4
    //   84: astore 8
    //   86: aload 4
    //   88: astore 6
    //   90: new 379	android/content/ContentValues
    //   93: dup
    //   94: invokespecial 380	android/content/ContentValues:<init>	()V
    //   97: astore 11
    //   99: aload 4
    //   101: astore 5
    //   103: aload 4
    //   105: astore 8
    //   107: aload 4
    //   109: astore 6
    //   111: aload 10
    //   113: ldc -87
    //   115: invokevirtual 224	org/json/JSONObject:optString	(Ljava/lang/String;)Ljava/lang/String;
    //   118: astore 9
    //   120: aload 9
    //   122: astore 7
    //   124: aload 4
    //   126: astore 5
    //   128: aload 4
    //   130: astore 8
    //   132: aload 4
    //   134: astore 6
    //   136: aload 9
    //   138: invokestatic 121	android/text/TextUtils:isEmpty	(Ljava/lang/CharSequence;)Z
    //   141: ifeq +50 -> 191
    //   144: aload 4
    //   146: astore 5
    //   148: aload 4
    //   150: astore 8
    //   152: aload 4
    //   154: astore 6
    //   156: getstatic 35	com/umeng/analytics/pro/w:c	Landroid/content/Context;
    //   159: invokestatic 382	com/umeng/analytics/pro/bd:g	(Landroid/content/Context;)Ljava/lang/String;
    //   162: astore 9
    //   164: aload 9
    //   166: astore 7
    //   168: aload 4
    //   170: astore 5
    //   172: aload 4
    //   174: astore 8
    //   176: aload 4
    //   178: astore 6
    //   180: aload 9
    //   182: invokestatic 121	android/text/TextUtils:isEmpty	(Ljava/lang/CharSequence;)Z
    //   185: ifeq +6 -> 191
    //   188: goto +328 -> 516
    //   191: aload 4
    //   193: astore 5
    //   195: aload 4
    //   197: astore 8
    //   199: aload 4
    //   201: astore 6
    //   203: aload 11
    //   205: ldc -87
    //   207: aload 7
    //   209: invokevirtual 385	android/content/ContentValues:put	(Ljava/lang/String;Ljava/lang/String;)V
    //   212: aload 4
    //   214: astore 5
    //   216: aload 4
    //   218: astore 8
    //   220: aload 4
    //   222: astore 6
    //   224: aload 11
    //   226: ldc_w 310
    //   229: aload 10
    //   231: ldc_w 327
    //   234: invokevirtual 224	org/json/JSONObject:optString	(Ljava/lang/String;)Ljava/lang/String;
    //   237: invokevirtual 385	android/content/ContentValues:put	(Ljava/lang/String;Ljava/lang/String;)V
    //   240: goto +283 -> 523
    //   243: aload 4
    //   245: astore 5
    //   247: aload 4
    //   249: astore 8
    //   251: aload 4
    //   253: astore 6
    //   255: aload 11
    //   257: ldc -93
    //   259: aload 10
    //   261: ldc -93
    //   263: invokevirtual 388	org/json/JSONObject:optInt	(Ljava/lang/String;)I
    //   266: invokestatic 392	java/lang/Integer:valueOf	(I)Ljava/lang/Integer;
    //   269: invokevirtual 395	android/content/ContentValues:put	(Ljava/lang/String;Ljava/lang/Integer;)V
    //   272: aload 4
    //   274: astore 5
    //   276: aload 4
    //   278: astore 8
    //   280: aload 4
    //   282: astore 6
    //   284: aload 10
    //   286: ldc -87
    //   288: invokevirtual 399	org/json/JSONObject:remove	(Ljava/lang/String;)Ljava/lang/Object;
    //   291: pop
    //   292: aload 4
    //   294: astore 5
    //   296: aload 4
    //   298: astore 8
    //   300: aload 4
    //   302: astore 6
    //   304: aload 10
    //   306: ldc -93
    //   308: invokevirtual 399	org/json/JSONObject:remove	(Ljava/lang/String;)Ljava/lang/Object;
    //   311: pop
    //   312: aload 4
    //   314: astore 5
    //   316: aload 4
    //   318: astore 8
    //   320: aload 4
    //   322: astore 6
    //   324: aload 11
    //   326: ldc -85
    //   328: aload_0
    //   329: aload 10
    //   331: invokevirtual 400	org/json/JSONObject:toString	()Ljava/lang/String;
    //   334: invokevirtual 131	com/umeng/analytics/pro/w:a	(Ljava/lang/String;)Ljava/lang/String;
    //   337: invokevirtual 385	android/content/ContentValues:put	(Ljava/lang/String;Ljava/lang/String;)V
    //   340: aload 4
    //   342: astore 5
    //   344: aload 4
    //   346: astore 8
    //   348: aload 4
    //   350: astore 6
    //   352: aload 4
    //   354: ldc_w 402
    //   357: aconst_null
    //   358: aload 11
    //   360: invokevirtual 406	android/database/sqlite/SQLiteDatabase:insert	(Ljava/lang/String;Ljava/lang/String;Landroid/content/ContentValues;)J
    //   363: pop2
    //   364: iload_2
    //   365: iconst_1
    //   366: iadd
    //   367: istore_2
    //   368: goto -331 -> 37
    //   371: aload 4
    //   373: astore 5
    //   375: aload 4
    //   377: astore 8
    //   379: aload 4
    //   381: astore 6
    //   383: aload 4
    //   385: invokevirtual 232	android/database/sqlite/SQLiteDatabase:setTransactionSuccessful	()V
    //   388: aload 4
    //   390: ifnull +8 -> 398
    //   393: aload 4
    //   395: invokevirtual 203	android/database/sqlite/SQLiteDatabase:endTransaction	()V
    //   398: getstatic 35	com/umeng/analytics/pro/w:c	Landroid/content/Context;
    //   401: invokestatic 150	com/umeng/analytics/pro/u:a	(Landroid/content/Context;)Lcom/umeng/analytics/pro/u;
    //   404: invokevirtual 204	com/umeng/analytics/pro/u:b	()V
    //   407: return
    //   408: astore_1
    //   409: aload 5
    //   411: astore 6
    //   413: getstatic 35	com/umeng/analytics/pro/w:c	Landroid/content/Context;
    //   416: invokestatic 200	com/umeng/analytics/pro/v:b	(Landroid/content/Context;)V
    //   419: aload 5
    //   421: ifnull +8 -> 429
    //   424: aload 5
    //   426: invokevirtual 203	android/database/sqlite/SQLiteDatabase:endTransaction	()V
    //   429: getstatic 35	com/umeng/analytics/pro/w:c	Landroid/content/Context;
    //   432: invokestatic 150	com/umeng/analytics/pro/u:a	(Landroid/content/Context;)Lcom/umeng/analytics/pro/u;
    //   435: invokevirtual 204	com/umeng/analytics/pro/u:b	()V
    //   438: return
    //   439: astore_1
    //   440: aload 8
    //   442: ifnull +8 -> 450
    //   445: aload 8
    //   447: invokevirtual 203	android/database/sqlite/SQLiteDatabase:endTransaction	()V
    //   450: getstatic 35	com/umeng/analytics/pro/w:c	Landroid/content/Context;
    //   453: invokestatic 150	com/umeng/analytics/pro/u:a	(Landroid/content/Context;)Lcom/umeng/analytics/pro/u;
    //   456: invokevirtual 204	com/umeng/analytics/pro/u:b	()V
    //   459: return
    //   460: astore_1
    //   461: aconst_null
    //   462: astore 6
    //   464: aload 6
    //   466: ifnull +8 -> 474
    //   469: aload 6
    //   471: invokevirtual 203	android/database/sqlite/SQLiteDatabase:endTransaction	()V
    //   474: getstatic 35	com/umeng/analytics/pro/w:c	Landroid/content/Context;
    //   477: invokestatic 150	com/umeng/analytics/pro/u:a	(Landroid/content/Context;)Lcom/umeng/analytics/pro/u;
    //   480: invokevirtual 204	com/umeng/analytics/pro/u:b	()V
    //   483: aload_1
    //   484: athrow
    //   485: astore_1
    //   486: goto -88 -> 398
    //   489: astore_1
    //   490: goto -61 -> 429
    //   493: astore_1
    //   494: goto -44 -> 450
    //   497: astore 4
    //   499: goto -25 -> 474
    //   502: astore_1
    //   503: goto -39 -> 464
    //   506: astore 5
    //   508: goto -144 -> 364
    //   511: iconst_0
    //   512: istore_2
    //   513: goto -476 -> 37
    //   516: ldc -83
    //   518: astore 7
    //   520: goto -329 -> 191
    //   523: goto -280 -> 243
    // Local variable table:
    //   start	length	slot	name	signature
    //   0	526	0	this	w
    //   0	526	1	paramJSONArray	org.json.JSONArray
    //   54	459	2	i	int
    //   53	4	3	j	int
    //   15	379	4	localSQLiteDatabase	android.database.sqlite.SQLiteDatabase
    //   497	1	4	localThrowable	Throwable
    //   4	421	5	localObject1	Object
    //   506	1	5	localException	Exception
    //   27	443	6	localObject2	Object
    //   122	397	7	str1	String
    //   1	445	8	localObject3	Object
    //   118	63	9	str2	String
    //   76	254	10	localJSONObject	JSONObject
    //   97	262	11	localContentValues	android.content.ContentValues
    // Exception table:
    //   from	to	target	type
    //   6	17	408	android/database/sqlite/SQLiteDatabaseCorruptException
    //   29	34	408	android/database/sqlite/SQLiteDatabaseCorruptException
    //   49	54	408	android/database/sqlite/SQLiteDatabaseCorruptException
    //   71	78	408	android/database/sqlite/SQLiteDatabaseCorruptException
    //   90	99	408	android/database/sqlite/SQLiteDatabaseCorruptException
    //   111	120	408	android/database/sqlite/SQLiteDatabaseCorruptException
    //   136	144	408	android/database/sqlite/SQLiteDatabaseCorruptException
    //   156	164	408	android/database/sqlite/SQLiteDatabaseCorruptException
    //   180	188	408	android/database/sqlite/SQLiteDatabaseCorruptException
    //   203	212	408	android/database/sqlite/SQLiteDatabaseCorruptException
    //   224	240	408	android/database/sqlite/SQLiteDatabaseCorruptException
    //   255	272	408	android/database/sqlite/SQLiteDatabaseCorruptException
    //   284	292	408	android/database/sqlite/SQLiteDatabaseCorruptException
    //   304	312	408	android/database/sqlite/SQLiteDatabaseCorruptException
    //   324	340	408	android/database/sqlite/SQLiteDatabaseCorruptException
    //   352	364	408	android/database/sqlite/SQLiteDatabaseCorruptException
    //   383	388	408	android/database/sqlite/SQLiteDatabaseCorruptException
    //   6	17	439	java/lang/Throwable
    //   29	34	439	java/lang/Throwable
    //   49	54	439	java/lang/Throwable
    //   71	78	439	java/lang/Throwable
    //   90	99	439	java/lang/Throwable
    //   111	120	439	java/lang/Throwable
    //   136	144	439	java/lang/Throwable
    //   156	164	439	java/lang/Throwable
    //   180	188	439	java/lang/Throwable
    //   203	212	439	java/lang/Throwable
    //   224	240	439	java/lang/Throwable
    //   255	272	439	java/lang/Throwable
    //   284	292	439	java/lang/Throwable
    //   304	312	439	java/lang/Throwable
    //   324	340	439	java/lang/Throwable
    //   352	364	439	java/lang/Throwable
    //   383	388	439	java/lang/Throwable
    //   6	17	460	finally
    //   393	398	485	java/lang/Throwable
    //   424	429	489	java/lang/Throwable
    //   445	450	493	java/lang/Throwable
    //   469	474	497	java/lang/Throwable
    //   29	34	502	finally
    //   49	54	502	finally
    //   71	78	502	finally
    //   90	99	502	finally
    //   111	120	502	finally
    //   136	144	502	finally
    //   156	164	502	finally
    //   180	188	502	finally
    //   203	212	502	finally
    //   224	240	502	finally
    //   255	272	502	finally
    //   284	292	502	finally
    //   304	312	502	finally
    //   324	340	502	finally
    //   352	364	502	finally
    //   383	388	502	finally
    //   413	419	502	finally
    //   71	78	506	java/lang/Exception
    //   90	99	506	java/lang/Exception
    //   111	120	506	java/lang/Exception
    //   136	144	506	java/lang/Exception
    //   156	164	506	java/lang/Exception
    //   180	188	506	java/lang/Exception
    //   203	212	506	java/lang/Exception
    //   224	240	506	java/lang/Exception
    //   255	272	506	java/lang/Exception
    //   284	292	506	java/lang/Exception
    //   304	312	506	java/lang/Exception
    //   324	340	506	java/lang/Exception
    //   352	364	506	java/lang/Exception
  }
  
  /* Error */
  public void a(boolean paramBoolean1, boolean paramBoolean2)
  {
    // Byte code:
    //   0: aconst_null
    //   1: astore 4
    //   3: getstatic 35	com/umeng/analytics/pro/w:c	Landroid/content/Context;
    //   6: invokestatic 150	com/umeng/analytics/pro/u:a	(Landroid/content/Context;)Lcom/umeng/analytics/pro/u;
    //   9: invokevirtual 153	com/umeng/analytics/pro/u:a	()Landroid/database/sqlite/SQLiteDatabase;
    //   12: astore 5
    //   14: aload 5
    //   16: astore 4
    //   18: aload 4
    //   20: invokevirtual 156	android/database/sqlite/SQLiteDatabase:beginTransaction	()V
    //   23: goto +263 -> 286
    //   26: aload 4
    //   28: ldc_w 408
    //   31: invokevirtual 138	android/database/sqlite/SQLiteDatabase:execSQL	(Ljava/lang/String;)V
    //   34: goto +255 -> 289
    //   37: aload 4
    //   39: ldc_w 410
    //   42: invokevirtual 138	android/database/sqlite/SQLiteDatabase:execSQL	(Ljava/lang/String;)V
    //   45: goto +247 -> 292
    //   48: aload 4
    //   50: ldc_w 412
    //   53: invokevirtual 138	android/database/sqlite/SQLiteDatabase:execSQL	(Ljava/lang/String;)V
    //   56: aload 4
    //   58: invokevirtual 232	android/database/sqlite/SQLiteDatabase:setTransactionSuccessful	()V
    //   61: aload 4
    //   63: ifnull +8 -> 71
    //   66: aload 4
    //   68: invokevirtual 203	android/database/sqlite/SQLiteDatabase:endTransaction	()V
    //   71: getstatic 35	com/umeng/analytics/pro/w:c	Landroid/content/Context;
    //   74: invokestatic 150	com/umeng/analytics/pro/u:a	(Landroid/content/Context;)Lcom/umeng/analytics/pro/u;
    //   77: invokevirtual 204	com/umeng/analytics/pro/u:b	()V
    //   80: return
    //   81: aload_0
    //   82: getfield 46	com/umeng/analytics/pro/w:h	Ljava/util/List;
    //   85: invokeinterface 415 1 0
    //   90: ifle +64 -> 154
    //   93: goto +210 -> 303
    //   96: iload_3
    //   97: aload_0
    //   98: getfield 46	com/umeng/analytics/pro/w:h	Ljava/util/List;
    //   101: invokeinterface 415 1 0
    //   106: if_icmpge +48 -> 154
    //   109: aload 4
    //   111: new 66	java/lang/StringBuilder
    //   114: dup
    //   115: invokespecial 67	java/lang/StringBuilder:<init>	()V
    //   118: ldc_w 417
    //   121: invokevirtual 73	java/lang/StringBuilder:append	(Ljava/lang/String;)Ljava/lang/StringBuilder;
    //   124: aload_0
    //   125: getfield 46	com/umeng/analytics/pro/w:h	Ljava/util/List;
    //   128: iload_3
    //   129: invokeinterface 421 2 0
    //   134: checkcast 175	java/lang/String
    //   137: invokevirtual 73	java/lang/StringBuilder:append	(Ljava/lang/String;)Ljava/lang/StringBuilder;
    //   140: ldc 85
    //   142: invokevirtual 73	java/lang/StringBuilder:append	(Ljava/lang/String;)Ljava/lang/StringBuilder;
    //   145: invokevirtual 89	java/lang/StringBuilder:toString	()Ljava/lang/String;
    //   148: invokevirtual 138	android/database/sqlite/SQLiteDatabase:execSQL	(Ljava/lang/String;)V
    //   151: goto +157 -> 308
    //   154: aload_0
    //   155: getfield 46	com/umeng/analytics/pro/w:h	Ljava/util/List;
    //   158: invokeinterface 53 1 0
    //   163: goto -107 -> 56
    //   166: astore 5
    //   168: getstatic 35	com/umeng/analytics/pro/w:c	Landroid/content/Context;
    //   171: invokestatic 200	com/umeng/analytics/pro/v:b	(Landroid/content/Context;)V
    //   174: aload 4
    //   176: ifnull +8 -> 184
    //   179: aload 4
    //   181: invokevirtual 203	android/database/sqlite/SQLiteDatabase:endTransaction	()V
    //   184: getstatic 35	com/umeng/analytics/pro/w:c	Landroid/content/Context;
    //   187: invokestatic 150	com/umeng/analytics/pro/u:a	(Landroid/content/Context;)Lcom/umeng/analytics/pro/u;
    //   190: invokevirtual 204	com/umeng/analytics/pro/u:b	()V
    //   193: return
    //   194: astore 4
    //   196: aconst_null
    //   197: astore 4
    //   199: aload 4
    //   201: ifnull +8 -> 209
    //   204: aload 4
    //   206: invokevirtual 203	android/database/sqlite/SQLiteDatabase:endTransaction	()V
    //   209: getstatic 35	com/umeng/analytics/pro/w:c	Landroid/content/Context;
    //   212: invokestatic 150	com/umeng/analytics/pro/u:a	(Landroid/content/Context;)Lcom/umeng/analytics/pro/u;
    //   215: invokevirtual 204	com/umeng/analytics/pro/u:b	()V
    //   218: return
    //   219: astore 5
    //   221: aconst_null
    //   222: astore 4
    //   224: aload 4
    //   226: ifnull +8 -> 234
    //   229: aload 4
    //   231: invokevirtual 203	android/database/sqlite/SQLiteDatabase:endTransaction	()V
    //   234: getstatic 35	com/umeng/analytics/pro/w:c	Landroid/content/Context;
    //   237: invokestatic 150	com/umeng/analytics/pro/u:a	(Landroid/content/Context;)Lcom/umeng/analytics/pro/u;
    //   240: invokevirtual 204	com/umeng/analytics/pro/u:b	()V
    //   243: aload 5
    //   245: athrow
    //   246: astore 4
    //   248: goto -177 -> 71
    //   251: astore 4
    //   253: goto -69 -> 184
    //   256: astore 4
    //   258: goto -49 -> 209
    //   261: astore 4
    //   263: goto -29 -> 234
    //   266: astore 5
    //   268: goto -44 -> 224
    //   271: astore 5
    //   273: goto -49 -> 224
    //   276: astore 5
    //   278: goto -79 -> 199
    //   281: astore 5
    //   283: goto -115 -> 168
    //   286: goto -260 -> 26
    //   289: goto -252 -> 37
    //   292: iload_2
    //   293: ifeq -212 -> 81
    //   296: iload_1
    //   297: ifeq -241 -> 56
    //   300: goto -252 -> 48
    //   303: iconst_0
    //   304: istore_3
    //   305: goto -209 -> 96
    //   308: iload_3
    //   309: iconst_1
    //   310: iadd
    //   311: istore_3
    //   312: goto -216 -> 96
    // Local variable table:
    //   start	length	slot	name	signature
    //   0	315	0	this	w
    //   0	315	1	paramBoolean1	boolean
    //   0	315	2	paramBoolean2	boolean
    //   96	216	3	i	int
    //   1	179	4	localObject1	Object
    //   194	1	4	localThrowable1	Throwable
    //   197	33	4	localObject2	Object
    //   246	1	4	localThrowable2	Throwable
    //   251	1	4	localThrowable3	Throwable
    //   256	1	4	localThrowable4	Throwable
    //   261	1	4	localThrowable5	Throwable
    //   12	3	5	localSQLiteDatabase	android.database.sqlite.SQLiteDatabase
    //   166	1	5	localSQLiteDatabaseCorruptException1	android.database.sqlite.SQLiteDatabaseCorruptException
    //   219	25	5	localObject3	Object
    //   266	1	5	localObject4	Object
    //   271	1	5	localObject5	Object
    //   276	1	5	localThrowable6	Throwable
    //   281	1	5	localSQLiteDatabaseCorruptException2	android.database.sqlite.SQLiteDatabaseCorruptException
    // Exception table:
    //   from	to	target	type
    //   18	23	166	android/database/sqlite/SQLiteDatabaseCorruptException
    //   26	34	166	android/database/sqlite/SQLiteDatabaseCorruptException
    //   37	45	166	android/database/sqlite/SQLiteDatabaseCorruptException
    //   48	56	166	android/database/sqlite/SQLiteDatabaseCorruptException
    //   56	61	166	android/database/sqlite/SQLiteDatabaseCorruptException
    //   81	93	166	android/database/sqlite/SQLiteDatabaseCorruptException
    //   96	151	166	android/database/sqlite/SQLiteDatabaseCorruptException
    //   154	163	166	android/database/sqlite/SQLiteDatabaseCorruptException
    //   3	14	194	java/lang/Throwable
    //   3	14	219	finally
    //   66	71	246	java/lang/Throwable
    //   179	184	251	java/lang/Throwable
    //   204	209	256	java/lang/Throwable
    //   229	234	261	java/lang/Throwable
    //   18	23	266	finally
    //   26	34	266	finally
    //   37	45	266	finally
    //   48	56	266	finally
    //   56	61	266	finally
    //   81	93	266	finally
    //   96	151	266	finally
    //   154	163	266	finally
    //   168	174	271	finally
    //   18	23	276	java/lang/Throwable
    //   26	34	276	java/lang/Throwable
    //   37	45	276	java/lang/Throwable
    //   48	56	276	java/lang/Throwable
    //   56	61	276	java/lang/Throwable
    //   81	93	276	java/lang/Throwable
    //   96	151	276	java/lang/Throwable
    //   154	163	276	java/lang/Throwable
    //   3	14	281	android/database/sqlite/SQLiteDatabaseCorruptException
  }
  
  /* Error */
  public boolean a(String paramString1, String paramString2, int paramInt)
  {
    // Byte code:
    //   0: aconst_null
    //   1: astore 7
    //   3: aconst_null
    //   4: astore 5
    //   6: getstatic 35	com/umeng/analytics/pro/w:c	Landroid/content/Context;
    //   9: invokestatic 150	com/umeng/analytics/pro/u:a	(Landroid/content/Context;)Lcom/umeng/analytics/pro/u;
    //   12: invokevirtual 153	com/umeng/analytics/pro/u:a	()Landroid/database/sqlite/SQLiteDatabase;
    //   15: astore 4
    //   17: aload 4
    //   19: astore 5
    //   21: aload 4
    //   23: astore 7
    //   25: aload 4
    //   27: astore 6
    //   29: aload 4
    //   31: invokevirtual 156	android/database/sqlite/SQLiteDatabase:beginTransaction	()V
    //   34: aload 4
    //   36: astore 5
    //   38: aload 4
    //   40: astore 7
    //   42: aload 4
    //   44: astore 6
    //   46: new 379	android/content/ContentValues
    //   49: dup
    //   50: invokespecial 380	android/content/ContentValues:<init>	()V
    //   53: astore 8
    //   55: aload 4
    //   57: astore 5
    //   59: aload 4
    //   61: astore 7
    //   63: aload 4
    //   65: astore 6
    //   67: aload 8
    //   69: ldc -87
    //   71: aload_1
    //   72: invokevirtual 385	android/content/ContentValues:put	(Ljava/lang/String;Ljava/lang/String;)V
    //   75: aload 4
    //   77: astore 5
    //   79: aload 4
    //   81: astore 7
    //   83: aload 4
    //   85: astore 6
    //   87: aload_0
    //   88: aload_2
    //   89: invokevirtual 131	com/umeng/analytics/pro/w:a	(Ljava/lang/String;)Ljava/lang/String;
    //   92: astore_1
    //   93: aload 4
    //   95: astore 5
    //   97: aload 4
    //   99: astore 7
    //   101: aload 4
    //   103: astore 6
    //   105: aload_1
    //   106: invokestatic 121	android/text/TextUtils:isEmpty	(Ljava/lang/CharSequence;)Z
    //   109: ifne +71 -> 180
    //   112: aload 4
    //   114: astore 5
    //   116: aload 4
    //   118: astore 7
    //   120: aload 4
    //   122: astore 6
    //   124: aload 8
    //   126: ldc_w 302
    //   129: aload_1
    //   130: invokevirtual 385	android/content/ContentValues:put	(Ljava/lang/String;Ljava/lang/String;)V
    //   133: aload 4
    //   135: astore 5
    //   137: aload 4
    //   139: astore 7
    //   141: aload 4
    //   143: astore 6
    //   145: aload 8
    //   147: ldc -93
    //   149: iload_3
    //   150: invokestatic 392	java/lang/Integer:valueOf	(I)Ljava/lang/Integer;
    //   153: invokevirtual 395	android/content/ContentValues:put	(Ljava/lang/String;Ljava/lang/Integer;)V
    //   156: aload 4
    //   158: astore 5
    //   160: aload 4
    //   162: astore 7
    //   164: aload 4
    //   166: astore 6
    //   168: aload 4
    //   170: ldc_w 424
    //   173: aconst_null
    //   174: aload 8
    //   176: invokevirtual 406	android/database/sqlite/SQLiteDatabase:insert	(Ljava/lang/String;Ljava/lang/String;Landroid/content/ContentValues;)J
    //   179: pop2
    //   180: aload 4
    //   182: astore 5
    //   184: aload 4
    //   186: astore 7
    //   188: aload 4
    //   190: astore 6
    //   192: aload 4
    //   194: invokevirtual 232	android/database/sqlite/SQLiteDatabase:setTransactionSuccessful	()V
    //   197: aload 4
    //   199: ifnull +8 -> 207
    //   202: aload 4
    //   204: invokevirtual 203	android/database/sqlite/SQLiteDatabase:endTransaction	()V
    //   207: getstatic 35	com/umeng/analytics/pro/w:c	Landroid/content/Context;
    //   210: invokestatic 150	com/umeng/analytics/pro/u:a	(Landroid/content/Context;)Lcom/umeng/analytics/pro/u;
    //   213: invokevirtual 204	com/umeng/analytics/pro/u:b	()V
    //   216: iconst_0
    //   217: ireturn
    //   218: astore_1
    //   219: aload 5
    //   221: astore 6
    //   223: getstatic 35	com/umeng/analytics/pro/w:c	Landroid/content/Context;
    //   226: invokestatic 200	com/umeng/analytics/pro/v:b	(Landroid/content/Context;)V
    //   229: aload 5
    //   231: ifnull +8 -> 239
    //   234: aload 5
    //   236: invokevirtual 203	android/database/sqlite/SQLiteDatabase:endTransaction	()V
    //   239: getstatic 35	com/umeng/analytics/pro/w:c	Landroid/content/Context;
    //   242: invokestatic 150	com/umeng/analytics/pro/u:a	(Landroid/content/Context;)Lcom/umeng/analytics/pro/u;
    //   245: invokevirtual 204	com/umeng/analytics/pro/u:b	()V
    //   248: goto -32 -> 216
    //   251: astore_1
    //   252: aload 7
    //   254: ifnull +8 -> 262
    //   257: aload 7
    //   259: invokevirtual 203	android/database/sqlite/SQLiteDatabase:endTransaction	()V
    //   262: getstatic 35	com/umeng/analytics/pro/w:c	Landroid/content/Context;
    //   265: invokestatic 150	com/umeng/analytics/pro/u:a	(Landroid/content/Context;)Lcom/umeng/analytics/pro/u;
    //   268: invokevirtual 204	com/umeng/analytics/pro/u:b	()V
    //   271: goto -55 -> 216
    //   274: astore_1
    //   275: aconst_null
    //   276: astore 6
    //   278: aload 6
    //   280: ifnull +8 -> 288
    //   283: aload 6
    //   285: invokevirtual 203	android/database/sqlite/SQLiteDatabase:endTransaction	()V
    //   288: getstatic 35	com/umeng/analytics/pro/w:c	Landroid/content/Context;
    //   291: invokestatic 150	com/umeng/analytics/pro/u:a	(Landroid/content/Context;)Lcom/umeng/analytics/pro/u;
    //   294: invokevirtual 204	com/umeng/analytics/pro/u:b	()V
    //   297: aload_1
    //   298: athrow
    //   299: astore_1
    //   300: goto -93 -> 207
    //   303: astore_1
    //   304: goto -65 -> 239
    //   307: astore_1
    //   308: goto -46 -> 262
    //   311: astore_2
    //   312: goto -24 -> 288
    //   315: astore_1
    //   316: goto -38 -> 278
    // Local variable table:
    //   start	length	slot	name	signature
    //   0	319	0	this	w
    //   0	319	1	paramString1	String
    //   0	319	2	paramString2	String
    //   0	319	3	paramInt	int
    //   15	188	4	localSQLiteDatabase	android.database.sqlite.SQLiteDatabase
    //   4	231	5	localObject1	Object
    //   27	257	6	localObject2	Object
    //   1	257	7	localObject3	Object
    //   53	122	8	localContentValues	android.content.ContentValues
    // Exception table:
    //   from	to	target	type
    //   6	17	218	android/database/sqlite/SQLiteDatabaseCorruptException
    //   29	34	218	android/database/sqlite/SQLiteDatabaseCorruptException
    //   46	55	218	android/database/sqlite/SQLiteDatabaseCorruptException
    //   67	75	218	android/database/sqlite/SQLiteDatabaseCorruptException
    //   87	93	218	android/database/sqlite/SQLiteDatabaseCorruptException
    //   105	112	218	android/database/sqlite/SQLiteDatabaseCorruptException
    //   124	133	218	android/database/sqlite/SQLiteDatabaseCorruptException
    //   145	156	218	android/database/sqlite/SQLiteDatabaseCorruptException
    //   168	180	218	android/database/sqlite/SQLiteDatabaseCorruptException
    //   192	197	218	android/database/sqlite/SQLiteDatabaseCorruptException
    //   6	17	251	java/lang/Throwable
    //   29	34	251	java/lang/Throwable
    //   46	55	251	java/lang/Throwable
    //   67	75	251	java/lang/Throwable
    //   87	93	251	java/lang/Throwable
    //   105	112	251	java/lang/Throwable
    //   124	133	251	java/lang/Throwable
    //   145	156	251	java/lang/Throwable
    //   168	180	251	java/lang/Throwable
    //   192	197	251	java/lang/Throwable
    //   6	17	274	finally
    //   202	207	299	java/lang/Throwable
    //   234	239	303	java/lang/Throwable
    //   257	262	307	java/lang/Throwable
    //   283	288	311	java/lang/Throwable
    //   29	34	315	finally
    //   46	55	315	finally
    //   67	75	315	finally
    //   87	93	315	finally
    //   105	112	315	finally
    //   124	133	315	finally
    //   145	156	315	finally
    //   168	180	315	finally
    //   192	197	315	finally
    //   223	229	315	finally
  }
  
  /* Error */
  public boolean a(String paramString, JSONObject paramJSONObject, a parama)
  {
    // Byte code:
    //   0: aconst_null
    //   1: astore 6
    //   3: aconst_null
    //   4: astore 7
    //   6: aconst_null
    //   7: astore 10
    //   9: aload_2
    //   10: ifnonnull +5 -> 15
    //   13: iconst_0
    //   14: ireturn
    //   15: getstatic 35	com/umeng/analytics/pro/w:c	Landroid/content/Context;
    //   18: invokestatic 150	com/umeng/analytics/pro/u:a	(Landroid/content/Context;)Lcom/umeng/analytics/pro/u;
    //   21: invokevirtual 153	com/umeng/analytics/pro/u:a	()Landroid/database/sqlite/SQLiteDatabase;
    //   24: astore 8
    //   26: aload 8
    //   28: astore 6
    //   30: aload 6
    //   32: invokevirtual 156	android/database/sqlite/SQLiteDatabase:beginTransaction	()V
    //   35: aload_3
    //   36: getstatic 428	com/umeng/analytics/pro/w$a:c	Lcom/umeng/analytics/pro/w$a;
    //   39: if_acmpne +102 -> 141
    //   42: aload_2
    //   43: ldc_w 310
    //   46: invokevirtual 430	org/json/JSONObject:get	(Ljava/lang/String;)Ljava/lang/Object;
    //   49: checkcast 312	java/lang/Long
    //   52: invokevirtual 434	java/lang/Long:longValue	()J
    //   55: lstore 4
    //   57: new 379	android/content/ContentValues
    //   60: dup
    //   61: invokespecial 380	android/content/ContentValues:<init>	()V
    //   64: astore_2
    //   65: aload_2
    //   66: ldc 81
    //   68: aload_1
    //   69: invokevirtual 385	android/content/ContentValues:put	(Ljava/lang/String;Ljava/lang/String;)V
    //   72: aload_2
    //   73: ldc_w 310
    //   76: lload 4
    //   78: invokestatic 437	java/lang/String:valueOf	(J)Ljava/lang/String;
    //   81: invokevirtual 385	android/content/ContentValues:put	(Ljava/lang/String;Ljava/lang/String;)V
    //   84: aload 6
    //   86: ldc 77
    //   88: aconst_null
    //   89: aload_2
    //   90: invokevirtual 406	android/database/sqlite/SQLiteDatabase:insert	(Ljava/lang/String;Ljava/lang/String;Landroid/content/ContentValues;)J
    //   93: pop2
    //   94: aconst_null
    //   95: astore_1
    //   96: aload_1
    //   97: astore 8
    //   99: aload_1
    //   100: astore 9
    //   102: aload_1
    //   103: astore 7
    //   105: aload 6
    //   107: invokevirtual 232	android/database/sqlite/SQLiteDatabase:setTransactionSuccessful	()V
    //   110: aload_1
    //   111: ifnull +9 -> 120
    //   114: aload_1
    //   115: invokeinterface 141 1 0
    //   120: aload 6
    //   122: ifnull +8 -> 130
    //   125: aload 6
    //   127: invokevirtual 203	android/database/sqlite/SQLiteDatabase:endTransaction	()V
    //   130: getstatic 35	com/umeng/analytics/pro/w:c	Landroid/content/Context;
    //   133: invokestatic 150	com/umeng/analytics/pro/u:a	(Landroid/content/Context;)Lcom/umeng/analytics/pro/u;
    //   136: invokevirtual 204	com/umeng/analytics/pro/u:b	()V
    //   139: iconst_0
    //   140: ireturn
    //   141: aload_3
    //   142: getstatic 439	com/umeng/analytics/pro/w$a:d	Lcom/umeng/analytics/pro/w$a;
    //   145: if_acmpne +73 -> 218
    //   148: aload_2
    //   149: ldc_w 308
    //   152: invokevirtual 430	org/json/JSONObject:get	(Ljava/lang/String;)Ljava/lang/Object;
    //   155: checkcast 312	java/lang/Long
    //   158: invokevirtual 434	java/lang/Long:longValue	()J
    //   161: lstore 4
    //   163: aload 6
    //   165: new 66	java/lang/StringBuilder
    //   168: dup
    //   169: invokespecial 67	java/lang/StringBuilder:<init>	()V
    //   172: ldc_w 441
    //   175: invokevirtual 73	java/lang/StringBuilder:append	(Ljava/lang/String;)Ljava/lang/StringBuilder;
    //   178: lload 4
    //   180: invokevirtual 444	java/lang/StringBuilder:append	(J)Ljava/lang/StringBuilder;
    //   183: ldc -121
    //   185: invokevirtual 73	java/lang/StringBuilder:append	(Ljava/lang/String;)Ljava/lang/StringBuilder;
    //   188: ldc 81
    //   190: invokevirtual 73	java/lang/StringBuilder:append	(Ljava/lang/String;)Ljava/lang/StringBuilder;
    //   193: ldc 83
    //   195: invokevirtual 73	java/lang/StringBuilder:append	(Ljava/lang/String;)Ljava/lang/StringBuilder;
    //   198: aload_1
    //   199: invokevirtual 73	java/lang/StringBuilder:append	(Ljava/lang/String;)Ljava/lang/StringBuilder;
    //   202: ldc 85
    //   204: invokevirtual 73	java/lang/StringBuilder:append	(Ljava/lang/String;)Ljava/lang/StringBuilder;
    //   207: invokevirtual 89	java/lang/StringBuilder:toString	()Ljava/lang/String;
    //   210: invokevirtual 138	android/database/sqlite/SQLiteDatabase:execSQL	(Ljava/lang/String;)V
    //   213: aconst_null
    //   214: astore_1
    //   215: goto +770 -> 985
    //   218: aload_3
    //   219: getstatic 446	com/umeng/analytics/pro/w$a:b	Lcom/umeng/analytics/pro/w$a;
    //   222: if_acmpne +19 -> 241
    //   225: aload_0
    //   226: aload_1
    //   227: aload_2
    //   228: aload 6
    //   230: ldc_w 302
    //   233: invokespecial 448	com/umeng/analytics/pro/w:a	(Ljava/lang/String;Lorg/json/JSONObject;Landroid/database/sqlite/SQLiteDatabase;Ljava/lang/String;)V
    //   236: aconst_null
    //   237: astore_1
    //   238: goto -142 -> 96
    //   241: aload_3
    //   242: getstatic 450	com/umeng/analytics/pro/w$a:a	Lcom/umeng/analytics/pro/w$a;
    //   245: if_acmpne +19 -> 264
    //   248: aload_0
    //   249: aload_1
    //   250: aload_2
    //   251: aload 6
    //   253: ldc_w 318
    //   256: invokespecial 448	com/umeng/analytics/pro/w:a	(Ljava/lang/String;Lorg/json/JSONObject;Landroid/database/sqlite/SQLiteDatabase;Ljava/lang/String;)V
    //   259: aconst_null
    //   260: astore_1
    //   261: goto -165 -> 96
    //   264: getstatic 452	com/umeng/analytics/pro/w$a:e	Lcom/umeng/analytics/pro/w$a;
    //   267: astore 8
    //   269: aload_3
    //   270: aload 8
    //   272: if_acmpne +708 -> 980
    //   275: aload_2
    //   276: ldc_w 322
    //   279: invokevirtual 455	org/json/JSONObject:getJSONObject	(Ljava/lang/String;)Lorg/json/JSONObject;
    //   282: astore 11
    //   284: aload 11
    //   286: ifnull +686 -> 972
    //   289: aload 6
    //   291: new 66	java/lang/StringBuilder
    //   294: dup
    //   295: invokespecial 67	java/lang/StringBuilder:<init>	()V
    //   298: ldc_w 457
    //   301: invokevirtual 73	java/lang/StringBuilder:append	(Ljava/lang/String;)Ljava/lang/StringBuilder;
    //   304: aload_1
    //   305: invokevirtual 73	java/lang/StringBuilder:append	(Ljava/lang/String;)Ljava/lang/StringBuilder;
    //   308: ldc 85
    //   310: invokevirtual 73	java/lang/StringBuilder:append	(Ljava/lang/String;)Ljava/lang/StringBuilder;
    //   313: invokevirtual 89	java/lang/StringBuilder:toString	()Ljava/lang/String;
    //   316: aconst_null
    //   317: invokevirtual 95	android/database/sqlite/SQLiteDatabase:rawQuery	(Ljava/lang/String;[Ljava/lang/String;)Landroid/database/Cursor;
    //   320: astore_3
    //   321: aload_3
    //   322: ifnull +644 -> 966
    //   325: aload_3
    //   326: astore 8
    //   328: aload_3
    //   329: astore 9
    //   331: aload_3
    //   332: astore 7
    //   334: aload_3
    //   335: invokeinterface 101 1 0
    //   340: ifeq +43 -> 383
    //   343: aload_3
    //   344: astore 8
    //   346: aload_3
    //   347: astore 9
    //   349: aload_3
    //   350: astore 7
    //   352: aload_0
    //   353: aload_3
    //   354: aload_3
    //   355: ldc_w 322
    //   358: invokeinterface 105 2 0
    //   363: invokeinterface 109 2 0
    //   368: invokevirtual 112	com/umeng/analytics/pro/w:b	(Ljava/lang/String;)Ljava/lang/String;
    //   371: astore 10
    //   373: goto -48 -> 325
    //   376: astore_3
    //   377: aconst_null
    //   378: astore 11
    //   380: goto -96 -> 284
    //   383: aload 11
    //   385: ifnull +171 -> 556
    //   388: aload_3
    //   389: astore 8
    //   391: aload_3
    //   392: astore 9
    //   394: aload_3
    //   395: astore 7
    //   397: new 114	org/json/JSONArray
    //   400: dup
    //   401: invokespecial 115	org/json/JSONArray:<init>	()V
    //   404: astore 12
    //   406: aload_3
    //   407: astore 8
    //   409: aload_3
    //   410: astore 9
    //   412: aload_3
    //   413: astore 7
    //   415: aload 10
    //   417: invokestatic 121	android/text/TextUtils:isEmpty	(Ljava/lang/CharSequence;)Z
    //   420: ifne +23 -> 443
    //   423: aload_3
    //   424: astore 8
    //   426: aload_3
    //   427: astore 9
    //   429: aload_3
    //   430: astore 7
    //   432: new 114	org/json/JSONArray
    //   435: dup
    //   436: aload 10
    //   438: invokespecial 124	org/json/JSONArray:<init>	(Ljava/lang/String;)V
    //   441: astore 12
    //   443: aload_3
    //   444: astore 8
    //   446: aload_3
    //   447: astore 9
    //   449: aload_3
    //   450: astore 7
    //   452: aload 12
    //   454: aload 11
    //   456: invokevirtual 128	org/json/JSONArray:put	(Ljava/lang/Object;)Lorg/json/JSONArray;
    //   459: pop
    //   460: aload_3
    //   461: astore 8
    //   463: aload_3
    //   464: astore 9
    //   466: aload_3
    //   467: astore 7
    //   469: aload_0
    //   470: aload 12
    //   472: invokevirtual 129	org/json/JSONArray:toString	()Ljava/lang/String;
    //   475: invokevirtual 131	com/umeng/analytics/pro/w:a	(Ljava/lang/String;)Ljava/lang/String;
    //   478: astore 10
    //   480: aload_3
    //   481: astore 8
    //   483: aload_3
    //   484: astore 9
    //   486: aload_3
    //   487: astore 7
    //   489: aload 10
    //   491: invokestatic 121	android/text/TextUtils:isEmpty	(Ljava/lang/CharSequence;)Z
    //   494: ifne +62 -> 556
    //   497: aload_3
    //   498: astore 8
    //   500: aload_3
    //   501: astore 9
    //   503: aload_3
    //   504: astore 7
    //   506: aload 6
    //   508: new 66	java/lang/StringBuilder
    //   511: dup
    //   512: invokespecial 67	java/lang/StringBuilder:<init>	()V
    //   515: ldc_w 459
    //   518: invokevirtual 73	java/lang/StringBuilder:append	(Ljava/lang/String;)Ljava/lang/StringBuilder;
    //   521: aload 10
    //   523: invokevirtual 73	java/lang/StringBuilder:append	(Ljava/lang/String;)Ljava/lang/StringBuilder;
    //   526: ldc -121
    //   528: invokevirtual 73	java/lang/StringBuilder:append	(Ljava/lang/String;)Ljava/lang/StringBuilder;
    //   531: ldc 81
    //   533: invokevirtual 73	java/lang/StringBuilder:append	(Ljava/lang/String;)Ljava/lang/StringBuilder;
    //   536: ldc 83
    //   538: invokevirtual 73	java/lang/StringBuilder:append	(Ljava/lang/String;)Ljava/lang/StringBuilder;
    //   541: aload_1
    //   542: invokevirtual 73	java/lang/StringBuilder:append	(Ljava/lang/String;)Ljava/lang/StringBuilder;
    //   545: ldc 85
    //   547: invokevirtual 73	java/lang/StringBuilder:append	(Ljava/lang/String;)Ljava/lang/StringBuilder;
    //   550: invokevirtual 89	java/lang/StringBuilder:toString	()Ljava/lang/String;
    //   553: invokevirtual 138	android/database/sqlite/SQLiteDatabase:execSQL	(Ljava/lang/String;)V
    //   556: aload_3
    //   557: astore 8
    //   559: aload_3
    //   560: astore 9
    //   562: aload_3
    //   563: astore 7
    //   565: aload_2
    //   566: ldc_w 320
    //   569: invokevirtual 455	org/json/JSONObject:getJSONObject	(Ljava/lang/String;)Lorg/json/JSONObject;
    //   572: astore 10
    //   574: goto +414 -> 988
    //   577: aload_3
    //   578: astore 8
    //   580: aload_3
    //   581: astore 9
    //   583: aload_3
    //   584: astore 7
    //   586: aload_0
    //   587: aload 10
    //   589: invokevirtual 400	org/json/JSONObject:toString	()Ljava/lang/String;
    //   592: invokevirtual 131	com/umeng/analytics/pro/w:a	(Ljava/lang/String;)Ljava/lang/String;
    //   595: astore 10
    //   597: aload_3
    //   598: astore 8
    //   600: aload_3
    //   601: astore 9
    //   603: aload_3
    //   604: astore 7
    //   606: aload 10
    //   608: invokestatic 121	android/text/TextUtils:isEmpty	(Ljava/lang/CharSequence;)Z
    //   611: ifne +62 -> 673
    //   614: aload_3
    //   615: astore 8
    //   617: aload_3
    //   618: astore 9
    //   620: aload_3
    //   621: astore 7
    //   623: aload 6
    //   625: new 66	java/lang/StringBuilder
    //   628: dup
    //   629: invokespecial 67	java/lang/StringBuilder:<init>	()V
    //   632: ldc_w 461
    //   635: invokevirtual 73	java/lang/StringBuilder:append	(Ljava/lang/String;)Ljava/lang/StringBuilder;
    //   638: aload 10
    //   640: invokevirtual 73	java/lang/StringBuilder:append	(Ljava/lang/String;)Ljava/lang/StringBuilder;
    //   643: ldc -121
    //   645: invokevirtual 73	java/lang/StringBuilder:append	(Ljava/lang/String;)Ljava/lang/StringBuilder;
    //   648: ldc 81
    //   650: invokevirtual 73	java/lang/StringBuilder:append	(Ljava/lang/String;)Ljava/lang/StringBuilder;
    //   653: ldc 83
    //   655: invokevirtual 73	java/lang/StringBuilder:append	(Ljava/lang/String;)Ljava/lang/StringBuilder;
    //   658: aload_1
    //   659: invokevirtual 73	java/lang/StringBuilder:append	(Ljava/lang/String;)Ljava/lang/StringBuilder;
    //   662: ldc 85
    //   664: invokevirtual 73	java/lang/StringBuilder:append	(Ljava/lang/String;)Ljava/lang/StringBuilder;
    //   667: invokevirtual 89	java/lang/StringBuilder:toString	()Ljava/lang/String;
    //   670: invokevirtual 138	android/database/sqlite/SQLiteDatabase:execSQL	(Ljava/lang/String;)V
    //   673: aload_3
    //   674: astore 8
    //   676: aload_3
    //   677: astore 9
    //   679: aload_3
    //   680: astore 7
    //   682: aload_2
    //   683: ldc_w 308
    //   686: invokevirtual 464	org/json/JSONObject:getLong	(Ljava/lang/String;)J
    //   689: lstore 4
    //   691: aload_3
    //   692: astore 8
    //   694: aload_3
    //   695: astore 9
    //   697: aload_3
    //   698: astore 7
    //   700: aload 6
    //   702: new 66	java/lang/StringBuilder
    //   705: dup
    //   706: invokespecial 67	java/lang/StringBuilder:<init>	()V
    //   709: ldc_w 466
    //   712: invokevirtual 73	java/lang/StringBuilder:append	(Ljava/lang/String;)Ljava/lang/StringBuilder;
    //   715: lload 4
    //   717: invokestatic 437	java/lang/String:valueOf	(J)Ljava/lang/String;
    //   720: invokevirtual 73	java/lang/StringBuilder:append	(Ljava/lang/String;)Ljava/lang/StringBuilder;
    //   723: ldc -121
    //   725: invokevirtual 73	java/lang/StringBuilder:append	(Ljava/lang/String;)Ljava/lang/StringBuilder;
    //   728: ldc 81
    //   730: invokevirtual 73	java/lang/StringBuilder:append	(Ljava/lang/String;)Ljava/lang/StringBuilder;
    //   733: ldc 83
    //   735: invokevirtual 73	java/lang/StringBuilder:append	(Ljava/lang/String;)Ljava/lang/StringBuilder;
    //   738: aload_1
    //   739: invokevirtual 73	java/lang/StringBuilder:append	(Ljava/lang/String;)Ljava/lang/StringBuilder;
    //   742: ldc 85
    //   744: invokevirtual 73	java/lang/StringBuilder:append	(Ljava/lang/String;)Ljava/lang/StringBuilder;
    //   747: invokevirtual 89	java/lang/StringBuilder:toString	()Ljava/lang/String;
    //   750: invokevirtual 138	android/database/sqlite/SQLiteDatabase:execSQL	(Ljava/lang/String;)V
    //   753: aload_3
    //   754: astore_1
    //   755: goto -659 -> 96
    //   758: astore_1
    //   759: aload_3
    //   760: astore_1
    //   761: goto -665 -> 96
    //   764: astore_1
    //   765: aconst_null
    //   766: astore 7
    //   768: aload 6
    //   770: astore_1
    //   771: getstatic 35	com/umeng/analytics/pro/w:c	Landroid/content/Context;
    //   774: invokestatic 200	com/umeng/analytics/pro/v:b	(Landroid/content/Context;)V
    //   777: aload 7
    //   779: ifnull +10 -> 789
    //   782: aload 7
    //   784: invokeinterface 141 1 0
    //   789: aload_1
    //   790: ifnull +7 -> 797
    //   793: aload_1
    //   794: invokevirtual 203	android/database/sqlite/SQLiteDatabase:endTransaction	()V
    //   797: getstatic 35	com/umeng/analytics/pro/w:c	Landroid/content/Context;
    //   800: invokestatic 150	com/umeng/analytics/pro/u:a	(Landroid/content/Context;)Lcom/umeng/analytics/pro/u;
    //   803: invokevirtual 204	com/umeng/analytics/pro/u:b	()V
    //   806: iconst_0
    //   807: ireturn
    //   808: astore_1
    //   809: aconst_null
    //   810: astore 9
    //   812: aconst_null
    //   813: astore 6
    //   815: aload 9
    //   817: ifnull +10 -> 827
    //   820: aload 9
    //   822: invokeinterface 141 1 0
    //   827: aload 6
    //   829: ifnull +8 -> 837
    //   832: aload 6
    //   834: invokevirtual 203	android/database/sqlite/SQLiteDatabase:endTransaction	()V
    //   837: getstatic 35	com/umeng/analytics/pro/w:c	Landroid/content/Context;
    //   840: invokestatic 150	com/umeng/analytics/pro/u:a	(Landroid/content/Context;)Lcom/umeng/analytics/pro/u;
    //   843: invokevirtual 204	com/umeng/analytics/pro/u:b	()V
    //   846: iconst_0
    //   847: ireturn
    //   848: astore_1
    //   849: aconst_null
    //   850: astore 6
    //   852: aload 7
    //   854: astore_2
    //   855: aload_2
    //   856: ifnull +9 -> 865
    //   859: aload_2
    //   860: invokeinterface 141 1 0
    //   865: aload 6
    //   867: ifnull +8 -> 875
    //   870: aload 6
    //   872: invokevirtual 203	android/database/sqlite/SQLiteDatabase:endTransaction	()V
    //   875: getstatic 35	com/umeng/analytics/pro/w:c	Landroid/content/Context;
    //   878: invokestatic 150	com/umeng/analytics/pro/u:a	(Landroid/content/Context;)Lcom/umeng/analytics/pro/u;
    //   881: invokevirtual 204	com/umeng/analytics/pro/u:b	()V
    //   884: aload_1
    //   885: athrow
    //   886: astore_1
    //   887: goto -757 -> 130
    //   890: astore_1
    //   891: goto -94 -> 797
    //   894: astore_1
    //   895: goto -58 -> 837
    //   898: astore_2
    //   899: goto -24 -> 875
    //   902: astore_1
    //   903: aload 7
    //   905: astore_2
    //   906: goto -51 -> 855
    //   909: astore_1
    //   910: aload 8
    //   912: astore_2
    //   913: goto -58 -> 855
    //   916: astore_3
    //   917: aload_1
    //   918: astore 6
    //   920: aload 7
    //   922: astore_2
    //   923: aload_3
    //   924: astore_1
    //   925: goto -70 -> 855
    //   928: astore_1
    //   929: aconst_null
    //   930: astore 9
    //   932: goto -117 -> 815
    //   935: astore_1
    //   936: goto -121 -> 815
    //   939: astore_1
    //   940: aconst_null
    //   941: astore 7
    //   943: aload 6
    //   945: astore_1
    //   946: goto -175 -> 771
    //   949: astore_1
    //   950: aload 6
    //   952: astore_1
    //   953: goto -182 -> 771
    //   956: astore 7
    //   958: goto -285 -> 673
    //   961: astore 7
    //   963: goto -407 -> 556
    //   966: aconst_null
    //   967: astore 10
    //   969: goto -586 -> 383
    //   972: aconst_null
    //   973: astore 10
    //   975: aconst_null
    //   976: astore_3
    //   977: goto -594 -> 383
    //   980: aconst_null
    //   981: astore_1
    //   982: goto -886 -> 96
    //   985: goto -889 -> 96
    //   988: aload 10
    //   990: ifnull -317 -> 673
    //   993: goto -416 -> 577
    // Local variable table:
    //   start	length	slot	name	signature
    //   0	996	0	this	w
    //   0	996	1	paramString	String
    //   0	996	2	paramJSONObject	JSONObject
    //   0	996	3	parama	a
    //   55	661	4	l	long
    //   1	950	6	localObject1	Object
    //   4	938	7	localObject2	Object
    //   956	1	7	localException1	Exception
    //   961	1	7	localException2	Exception
    //   24	887	8	localObject3	Object
    //   100	831	9	localObject4	Object
    //   7	982	10	localObject5	Object
    //   282	173	11	localJSONObject	JSONObject
    //   404	67	12	localJSONArray	org.json.JSONArray
    // Exception table:
    //   from	to	target	type
    //   275	284	376	java/lang/Exception
    //   682	691	758	java/lang/Exception
    //   700	753	758	java/lang/Exception
    //   15	26	764	android/database/sqlite/SQLiteDatabaseCorruptException
    //   15	26	808	java/lang/Throwable
    //   15	26	848	finally
    //   125	130	886	java/lang/Throwable
    //   793	797	890	java/lang/Throwable
    //   832	837	894	java/lang/Throwable
    //   870	875	898	java/lang/Throwable
    //   30	94	902	finally
    //   141	213	902	finally
    //   218	236	902	finally
    //   241	259	902	finally
    //   264	269	902	finally
    //   275	284	902	finally
    //   289	321	902	finally
    //   105	110	909	finally
    //   334	343	909	finally
    //   352	373	909	finally
    //   397	406	909	finally
    //   415	423	909	finally
    //   432	443	909	finally
    //   452	460	909	finally
    //   469	480	909	finally
    //   489	497	909	finally
    //   506	556	909	finally
    //   565	574	909	finally
    //   586	597	909	finally
    //   606	614	909	finally
    //   623	673	909	finally
    //   682	691	909	finally
    //   700	753	909	finally
    //   771	777	916	finally
    //   30	94	928	java/lang/Throwable
    //   141	213	928	java/lang/Throwable
    //   218	236	928	java/lang/Throwable
    //   241	259	928	java/lang/Throwable
    //   264	269	928	java/lang/Throwable
    //   275	284	928	java/lang/Throwable
    //   289	321	928	java/lang/Throwable
    //   105	110	935	java/lang/Throwable
    //   334	343	935	java/lang/Throwable
    //   352	373	935	java/lang/Throwable
    //   397	406	935	java/lang/Throwable
    //   415	423	935	java/lang/Throwable
    //   432	443	935	java/lang/Throwable
    //   452	460	935	java/lang/Throwable
    //   469	480	935	java/lang/Throwable
    //   489	497	935	java/lang/Throwable
    //   506	556	935	java/lang/Throwable
    //   565	574	935	java/lang/Throwable
    //   586	597	935	java/lang/Throwable
    //   606	614	935	java/lang/Throwable
    //   623	673	935	java/lang/Throwable
    //   682	691	935	java/lang/Throwable
    //   700	753	935	java/lang/Throwable
    //   30	94	939	android/database/sqlite/SQLiteDatabaseCorruptException
    //   141	213	939	android/database/sqlite/SQLiteDatabaseCorruptException
    //   218	236	939	android/database/sqlite/SQLiteDatabaseCorruptException
    //   241	259	939	android/database/sqlite/SQLiteDatabaseCorruptException
    //   264	269	939	android/database/sqlite/SQLiteDatabaseCorruptException
    //   275	284	939	android/database/sqlite/SQLiteDatabaseCorruptException
    //   289	321	939	android/database/sqlite/SQLiteDatabaseCorruptException
    //   105	110	949	android/database/sqlite/SQLiteDatabaseCorruptException
    //   334	343	949	android/database/sqlite/SQLiteDatabaseCorruptException
    //   352	373	949	android/database/sqlite/SQLiteDatabaseCorruptException
    //   397	406	949	android/database/sqlite/SQLiteDatabaseCorruptException
    //   415	423	949	android/database/sqlite/SQLiteDatabaseCorruptException
    //   432	443	949	android/database/sqlite/SQLiteDatabaseCorruptException
    //   452	460	949	android/database/sqlite/SQLiteDatabaseCorruptException
    //   469	480	949	android/database/sqlite/SQLiteDatabaseCorruptException
    //   489	497	949	android/database/sqlite/SQLiteDatabaseCorruptException
    //   506	556	949	android/database/sqlite/SQLiteDatabaseCorruptException
    //   565	574	949	android/database/sqlite/SQLiteDatabaseCorruptException
    //   586	597	949	android/database/sqlite/SQLiteDatabaseCorruptException
    //   606	614	949	android/database/sqlite/SQLiteDatabaseCorruptException
    //   623	673	949	android/database/sqlite/SQLiteDatabaseCorruptException
    //   682	691	949	android/database/sqlite/SQLiteDatabaseCorruptException
    //   700	753	949	android/database/sqlite/SQLiteDatabaseCorruptException
    //   565	574	956	java/lang/Exception
    //   586	597	956	java/lang/Exception
    //   606	614	956	java/lang/Exception
    //   623	673	956	java/lang/Exception
    //   397	406	961	java/lang/Exception
    //   415	423	961	java/lang/Exception
    //   432	443	961	java/lang/Exception
    //   452	460	961	java/lang/Exception
    //   469	480	961	java/lang/Exception
    //   489	497	961	java/lang/Exception
    //   506	556	961	java/lang/Exception
  }
  
  public String b(String paramString)
  {
    try
    {
      if (TextUtils.isEmpty(d)) {
        return paramString;
      }
      paramString = new String(bt.b(Base64.decode(paramString.getBytes(), 0), d.getBytes()));
      return paramString;
    }
    catch (Exception paramString) {}
    return null;
  }
  
  public static enum a
  {
    private a() {}
  }
  
  private static class b
  {
    private static final w a = new w(null);
  }
}


/* Location:              C:\Users\Marcus Cheung\Desktop\AndriodHacking\Makeblock_v3.0.8_apkpure.com-dex2jar.jar!\com\umeng\analytics\pro\w.class
 * Java compiler version: 6 (50.0)
 * JD-Core Version:       0.7.1
 */